{
  "updated_at": "2026-07-01T19:05:41+08:00",
  "trading_days": [
    "2026-06-24",
    "2026-06-25",
    "2026-06-26",
    "2026-06-29",
    "2026-06-30",
    "2026-07-01"
  ],
  "note": "數值單位為「張」(股數÷1000);外資含陸資、自營商含自行+避險。資料僅供參考,非投資建議。",
  "stocks": [
    {
      "code": "2303",
      "name": "聯電",
      "market": "TWSE",
      "foreign_daily": [
        7333,
        11768,
        -16701,
        -15741,
        35206,
        65874
      ],
      "dealer_daily": [
        9436,
        3926,
        -2532,
        -1603,
        5133,
        5661
      ]
    },
    {
      "code": "2610",
      "name": "華航",
      "market": "TWSE",
      "foreign_daily": [
        61357,
        52216,
        3664,
        455,
        -13232,
        -41399
      ],
      "dealer_daily": [
        7519,
        3236,
        -1801,
        454,
        -232,
        -762
      ]
    },
    {
      "code": "1301",
      "name": "台塑",
      "market": "TWSE",
      "foreign_daily": [
        20646,
        39475,
        -23336,
        5988,
        7914,
        3110
      ],
      "dealer_daily": [
        1164,
        -8,
        -1596,
        -2,
        676,
        146
      ]
    },
    {
      "code": "1102",
      "name": "亞泥",
      "market": "TWSE",
      "foreign_daily": [
        980,
        1336,
        3929,
        768,
        1678,
        42427
      ],
      "dealer_daily": [
        96,
        1061,
        178,
        908,
        1100,
        2356
      ]
    },
    {
      "code": "2449",
      "name": "京元電子",
      "market": "TWSE",
      "foreign_daily": [
        3806,
        7790,
        2555,
        -2745,
        15739,
        5213
      ],
      "dealer_daily": [
        -108,
        258,
        -418,
        52,
        935,
        -154
      ]
    },
    {
      "code": "5880",
      "name": "合庫金",
      "market": "TWSE",
      "foreign_daily": [
        2563,
        23418,
        837,
        3789,
        425,
        614
      ],
      "dealer_daily": [
        465,
        108,
        555,
        238,
        97,
        172
      ]
    },
    {
      "code": "2406",
      "name": "國碩",
      "market": "TWSE",
      "foreign_daily": [
        -601,
        -126,
        -1455,
        2115,
        8346,
        16838
      ],
      "dealer_daily": [
        -2,
        -9,
        -2,
        231,
        38,
        121
      ]
    },
    {
      "code": "4938",
      "name": "和碩",
      "market": "TWSE",
      "foreign_daily": [
        7649,
        5618,
        -5282,
        7919,
        2794,
        3285
      ],
      "dealer_daily": [
        314,
        279,
        -124,
        474,
        155,
        -76
      ]
    },
    {
      "code": "2881",
      "name": "富邦金",
      "market": "TWSE",
      "foreign_daily": [
        -4374,
        -627,
        147,
        -2022,
        -2906,
        29531
      ],
      "dealer_daily": [
        378,
        -156,
        287,
        368,
        -38,
        -490
      ]
    },
    {
      "code": "8046",
      "name": "南電",
      "market": "TWSE",
      "foreign_daily": [
        3229,
        4303,
        3130,
        2359,
        -676,
        2431
      ],
      "dealer_daily": [
        368,
        297,
        -843,
        44,
        297,
        -34
      ]
    },
    {
      "code": "8033",
      "name": "雷虎",
      "market": "TWSE",
      "foreign_daily": [
        -164,
        -283,
        165,
        35,
        6038,
        7489
      ],
      "dealer_daily": [
        -31,
        0,
        -1,
        194,
        567,
        119
      ]
    },
    {
      "code": "2105",
      "name": "正新",
      "market": "TWSE",
      "foreign_daily": [
        -276,
        6219,
        2333,
        6734,
        -5244,
        2084
      ],
      "dealer_daily": [
        -49,
        77,
        78,
        93,
        -19,
        49
      ]
    },
    {
      "code": "2812",
      "name": "台中銀",
      "market": "TWSE",
      "foreign_daily": [
        870,
        7521,
        446,
        1971,
        3675,
        -2852
      ],
      "dealer_daily": [
        111,
        121,
        118,
        29,
        7,
        -54
      ]
    },
    {
      "code": "1710",
      "name": "東聯",
      "market": "TWSE",
      "foreign_daily": [
        892,
        111,
        1272,
        -1388,
        8230,
        2095
      ],
      "dealer_daily": [
        -5,
        8,
        42,
        292,
        139,
        52
      ]
    },
    {
      "code": "2363",
      "name": "矽統",
      "market": "TWSE",
      "foreign_daily": [
        1625,
        1839,
        -6119,
        -551,
        -5028,
        19230
      ],
      "dealer_daily": [
        555,
        547,
        -974,
        17,
        35,
        1170
      ]
    },
    {
      "code": "5483",
      "name": "中美晶",
      "market": "TPEX",
      "foreign_daily": [
        -3269,
        -888,
        -1631,
        161,
        1885,
        14305
      ],
      "dealer_daily": [
        -188,
        343,
        -434,
        -160,
        416,
        435
      ]
    },
    {
      "code": "1714",
      "name": "和桐",
      "market": "TWSE",
      "foreign_daily": [
        3384,
        2691,
        1711,
        415,
        1270,
        819
      ],
      "dealer_daily": [
        259,
        -60,
        338,
        39,
        -57,
        25
      ]
    },
    {
      "code": "1319",
      "name": "東陽",
      "market": "TWSE",
      "foreign_daily": [
        5723,
        3128,
        -170,
        1509,
        726,
        -1322
      ],
      "dealer_daily": [
        -182,
        170,
        102,
        100,
        53,
        13
      ]
    },
    {
      "code": "2634",
      "name": "漢翔",
      "market": "TWSE",
      "foreign_daily": [
        -262,
        -1654,
        1036,
        -3355,
        18919,
        -5768
      ],
      "dealer_daily": [
        -11,
        -32,
        88,
        671,
        649,
        262
      ]
    },
    {
      "code": "2464",
      "name": "盟立",
      "market": "TWSE",
      "foreign_daily": [
        484,
        -2416,
        2057,
        669,
        -215,
        7018
      ],
      "dealer_daily": [
        -40,
        -140,
        -115,
        12,
        20,
        283
      ]
    },
    {
      "code": "3221",
      "name": "台嘉碩",
      "market": "TPEX",
      "foreign_daily": [
        -398,
        -12,
        2150,
        -1631,
        244,
        7125
      ],
      "dealer_daily": [
        -1,
        -13,
        128,
        -3,
        24,
        116
      ]
    },
    {
      "code": "2484",
      "name": "希華",
      "market": "TWSE",
      "foreign_daily": [
        -268,
        -850,
        3342,
        1025,
        1697,
        2050
      ],
      "dealer_daily": [
        47,
        -22,
        289,
        -294,
        -30,
        213
      ]
    },
    {
      "code": "2515",
      "name": "中工",
      "market": "TWSE",
      "foreign_daily": [
        -546,
        -491,
        1639,
        -1696,
        3484,
        4061
      ],
      "dealer_daily": [
        43,
        51,
        52,
        -3,
        -1,
        5
      ]
    },
    {
      "code": "6213",
      "name": "聯茂",
      "market": "TWSE",
      "foreign_daily": [
        3765,
        3957,
        3833,
        -1708,
        -2010,
        -1405
      ],
      "dealer_daily": [
        194,
        174,
        91,
        156,
        975,
        -224
      ]
    },
    {
      "code": "2368",
      "name": "金像電",
      "market": "TWSE",
      "foreign_daily": [
        1083,
        1598,
        1993,
        1594,
        -221,
        116
      ],
      "dealer_daily": [
        99,
        -35,
        -135,
        -5,
        60,
        24
      ]
    },
    {
      "code": "2618",
      "name": "長榮航",
      "market": "TWSE",
      "foreign_daily": [
        25401,
        13423,
        7123,
        -5959,
        -10225,
        -23657
      ],
      "dealer_daily": [
        1719,
        524,
        -369,
        169,
        452,
        -1170
      ]
    },
    {
      "code": "3413",
      "name": "京鼎",
      "market": "TWSE",
      "foreign_daily": [
        -37,
        -202,
        -445,
        580,
        4200,
        1888
      ],
      "dealer_daily": [
        19,
        -14,
        -43,
        62,
        124,
        7
      ]
    },
    {
      "code": "2885",
      "name": "元大金",
      "market": "TWSE",
      "foreign_daily": [
        -8355,
        12081,
        7331,
        6352,
        -8587,
        -2942
      ],
      "dealer_daily": [
        -950,
        100,
        1134,
        450,
        -27,
        604
      ]
    },
    {
      "code": "3264",
      "name": "欣銓",
      "market": "TPEX",
      "foreign_daily": [
        228,
        226,
        -193,
        -211,
        2055,
        3368
      ],
      "dealer_daily": [
        -53,
        -50,
        -109,
        120,
        102,
        185
      ]
    },
    {
      "code": "3227",
      "name": "原相",
      "market": "TPEX",
      "foreign_daily": [
        -99,
        1490,
        -1294,
        1200,
        2291,
        1726
      ],
      "dealer_daily": [
        -38,
        80,
        -242,
        143,
        41,
        120
      ]
    },
    {
      "code": "3236",
      "name": "千如",
      "market": "TPEX",
      "foreign_daily": [
        -1376,
        1041,
        1212,
        -1029,
        -880,
        6250
      ],
      "dealer_daily": [
        -7,
        82,
        -43,
        -44,
        141,
        -51
      ]
    },
    {
      "code": "1477",
      "name": "聚陽",
      "market": "TWSE",
      "foreign_daily": [
        3796,
        2757,
        -693,
        403,
        -1148,
        -412
      ],
      "dealer_daily": [
        85,
        100,
        63,
        -16,
        2,
        56
      ]
    },
    {
      "code": "1326",
      "name": "台化",
      "market": "TWSE",
      "foreign_daily": [
        20605,
        5900,
        -18103,
        -1572,
        -3272,
        1054
      ],
      "dealer_daily": [
        867,
        477,
        -1148,
        88,
        323,
        601
      ]
    },
    {
      "code": "6672",
      "name": "騰輝電子-KY",
      "market": "TWSE",
      "foreign_daily": [
        279,
        2843,
        491,
        -576,
        25,
        1163
      ],
      "dealer_daily": [
        69,
        110,
        -89,
        -33,
        98,
        -39
      ]
    },
    {
      "code": "6271",
      "name": "同欣電",
      "market": "TWSE",
      "foreign_daily": [
        -1109,
        1756,
        -2119,
        -133,
        4714,
        798
      ],
      "dealer_daily": [
        31,
        272,
        -117,
        -261,
        269,
        966
      ]
    },
    {
      "code": "2478",
      "name": "大毅",
      "market": "TWSE",
      "foreign_daily": [
        1287,
        461,
        321,
        428,
        433,
        769
      ],
      "dealer_daily": [
        21,
        3,
        30,
        1,
        -2,
        1
      ]
    },
    {
      "code": "1308",
      "name": "亞聚",
      "market": "TWSE",
      "foreign_daily": [
        1622,
        845,
        55,
        -15,
        -119,
        1145
      ],
      "dealer_daily": [
        41,
        -3,
        -13,
        -1,
        12,
        -3
      ]
    },
    {
      "code": "3624",
      "name": "光頡",
      "market": "TPEX",
      "foreign_daily": [
        762,
        729,
        203,
        712,
        542,
        538
      ],
      "dealer_daily": [
        19,
        32,
        25,
        25,
        94,
        62
      ]
    },
    {
      "code": "6509",
      "name": "聚和",
      "market": "TPEX",
      "foreign_daily": [
        377,
        -99,
        189,
        821,
        746,
        1421
      ],
      "dealer_daily": [
        6,
        27,
        -27,
        1,
        14,
        50
      ]
    },
    {
      "code": "1810",
      "name": "和成",
      "market": "TWSE",
      "foreign_daily": [
        -223,
        -20,
        -139,
        259,
        2761,
        705
      ],
      "dealer_daily": [
        1,
        1,
        7,
        6,
        19,
        -18
      ]
    },
    {
      "code": "3010",
      "name": "華立",
      "market": "TWSE",
      "foreign_daily": [
        528,
        666,
        295,
        912,
        1319,
        -434
      ],
      "dealer_daily": [
        4,
        -11,
        -9,
        11,
        52,
        4
      ]
    },
    {
      "code": "8016",
      "name": "矽創",
      "market": "TWSE",
      "foreign_daily": [
        301,
        958,
        532,
        -12,
        694,
        793
      ],
      "dealer_daily": [
        4,
        48,
        -35,
        -6,
        97,
        23
      ]
    },
    {
      "code": "4532",
      "name": "瑞智",
      "market": "TWSE",
      "foreign_daily": [
        372,
        763,
        -311,
        1297,
        851,
        142
      ],
      "dealer_daily": [
        -3,
        0,
        -2,
        30,
        400,
        -62
      ]
    },
    {
      "code": "2645",
      "name": "長榮航太",
      "market": "TWSE",
      "foreign_daily": [
        166,
        -31,
        247,
        -201,
        1912,
        878
      ],
      "dealer_daily": [
        1,
        1,
        -1,
        18,
        369,
        139
      ]
    },
    {
      "code": "4526",
      "name": "東台",
      "market": "TWSE",
      "foreign_daily": [
        182,
        -1652,
        -138,
        -421,
        1556,
        3178
      ],
      "dealer_daily": [
        14,
        11,
        -35,
        -18,
        75,
        4
      ]
    },
    {
      "code": "6757",
      "name": "台灣虎航",
      "market": "TWSE",
      "foreign_daily": [
        -688,
        2620,
        1,
        145,
        -68,
        672
      ],
      "dealer_daily": [
        392,
        89,
        -405,
        -49,
        -7,
        2
      ]
    },
    {
      "code": "4123",
      "name": "晟德",
      "market": "TPEX",
      "foreign_daily": [
        1240,
        1,
        -343,
        1007,
        166,
        470
      ],
      "dealer_daily": [
        10,
        -2,
        -6,
        19,
        3,
        -1
      ]
    },
    {
      "code": "3363",
      "name": "上詮",
      "market": "TPEX",
      "foreign_daily": [
        50,
        676,
        1343,
        46,
        13,
        357
      ],
      "dealer_daily": [
        0,
        0,
        -12,
        -3,
        0,
        68
      ]
    },
    {
      "code": "3028",
      "name": "增你強",
      "market": "TWSE",
      "foreign_daily": [
        -64,
        -711,
        2914,
        -275,
        1128,
        -604
      ],
      "dealer_daily": [
        12,
        -25,
        76,
        21,
        30,
        -69
      ]
    },
    {
      "code": "2103",
      "name": "台橡",
      "market": "TWSE",
      "foreign_daily": [
        2561,
        144,
        -1008,
        586,
        109,
        -23
      ],
      "dealer_daily": [
        191,
        -87,
        -24,
        15,
        -4,
        -5
      ]
    },
    {
      "code": "5443",
      "name": "均豪",
      "market": "TPEX",
      "foreign_daily": [
        -303,
        -344,
        -200,
        732,
        -190,
        2592
      ],
      "dealer_daily": [
        27,
        -25,
        -44,
        38,
        42,
        264
      ]
    },
    {
      "code": "3044",
      "name": "健鼎",
      "market": "TWSE",
      "foreign_daily": [
        -1054,
        100,
        -100,
        394,
        626,
        2249
      ],
      "dealer_daily": [
        -41,
        1,
        34,
        15,
        87,
        -4
      ]
    },
    {
      "code": "1210",
      "name": "大成",
      "market": "TWSE",
      "foreign_daily": [
        555,
        1589,
        -378,
        -203,
        362,
        276
      ],
      "dealer_daily": [
        17,
        153,
        5,
        126,
        75,
        135
      ]
    },
    {
      "code": "6753",
      "name": "龍德造船",
      "market": "TWSE",
      "foreign_daily": [
        -44,
        -87,
        13,
        60,
        743,
        1447
      ],
      "dealer_daily": [
        -11,
        -13,
        1,
        194,
        180,
        294
      ]
    },
    {
      "code": "3717",
      "name": "聯嘉投控",
      "market": "TWSE",
      "foreign_daily": [
        -498,
        -817,
        3428,
        -1244,
        69,
        1104
      ],
      "dealer_daily": [
        11,
        -20,
        -112,
        -9,
        -197,
        877
      ]
    },
    {
      "code": "4766",
      "name": "南寶",
      "market": "TWSE",
      "foreign_daily": [
        50,
        550,
        8,
        854,
        310,
        239
      ],
      "dealer_daily": [
        -6,
        0,
        -4,
        -3,
        2,
        17
      ]
    },
    {
      "code": "1229",
      "name": "聯華",
      "market": "TWSE",
      "foreign_daily": [
        2206,
        2171,
        -841,
        -548,
        -101,
        -900
      ],
      "dealer_daily": [
        -1,
        -6,
        57,
        8,
        4,
        -3
      ]
    },
    {
      "code": "2466",
      "name": "冠西電",
      "market": "TWSE",
      "foreign_daily": [
        167,
        -201,
        179,
        60,
        595,
        1130
      ],
      "dealer_daily": [
        0,
        0,
        1,
        -2,
        7,
        -5
      ]
    },
    {
      "code": "1309",
      "name": "台達化",
      "market": "TWSE",
      "foreign_daily": [
        682,
        -170,
        385,
        516,
        463,
        -102
      ],
      "dealer_daily": [
        33,
        -4,
        18,
        -27,
        -11,
        1
      ]
    },
    {
      "code": "6156",
      "name": "松上",
      "market": "TPEX",
      "foreign_daily": [
        -510,
        522,
        116,
        550,
        517,
        494
      ],
      "dealer_daily": [
        -59,
        -10,
        -61,
        0,
        100,
        36
      ]
    },
    {
      "code": "3680",
      "name": "家登",
      "market": "TPEX",
      "foreign_daily": [
        -372,
        13,
        255,
        424,
        443,
        912
      ],
      "dealer_daily": [
        -65,
        10,
        -72,
        -13,
        61,
        209
      ]
    },
    {
      "code": "3402",
      "name": "漢科",
      "market": "TPEX",
      "foreign_daily": [
        53,
        1111,
        -189,
        117,
        237,
        327
      ],
      "dealer_daily": [
        -1,
        31,
        -5,
        -11,
        0,
        14
      ]
    },
    {
      "code": "2342",
      "name": "茂矽",
      "market": "TWSE",
      "foreign_daily": [
        598,
        18,
        408,
        544,
        144,
        -58
      ],
      "dealer_daily": [
        4,
        0,
        137,
        -27,
        -19,
        -9
      ]
    },
    {
      "code": "6189",
      "name": "豐藝",
      "market": "TWSE",
      "foreign_daily": [
        102,
        -633,
        640,
        -133,
        217,
        1396
      ],
      "dealer_daily": [
        6,
        5,
        6,
        -6,
        4,
        8
      ]
    },
    {
      "code": "3081",
      "name": "聯亞",
      "market": "TPEX",
      "foreign_daily": [
        371,
        474,
        152,
        391,
        -12,
        166
      ],
      "dealer_daily": [
        -78,
        0,
        -9,
        76,
        6,
        27
      ]
    },
    {
      "code": "2527",
      "name": "宏璟",
      "market": "TWSE",
      "foreign_daily": [
        21,
        403,
        941,
        -392,
        329,
        211
      ],
      "dealer_daily": [
        4,
        0,
        -2,
        0,
        -1,
        0
      ]
    },
    {
      "code": "2547",
      "name": "日勝生",
      "market": "TWSE",
      "foreign_daily": [
        115,
        1168,
        603,
        945,
        -901,
        -433
      ],
      "dealer_daily": [
        3,
        9,
        1,
        0,
        -2,
        -10
      ]
    },
    {
      "code": "5512",
      "name": "力麒",
      "market": "TPEX",
      "foreign_daily": [
        117,
        331,
        379,
        584,
        -204,
        265
      ],
      "dealer_daily": [
        0,
        0,
        0,
        0,
        0,
        1
      ]
    },
    {
      "code": "2395",
      "name": "研華",
      "market": "TWSE",
      "foreign_daily": [
        -665,
        355,
        -536,
        800,
        874,
        627
      ],
      "dealer_daily": [
        17,
        -61,
        -26,
        24,
        31,
        33
      ]
    },
    {
      "code": "3583",
      "name": "辛耘",
      "market": "TWSE",
      "foreign_daily": [
        -203,
        -18,
        154,
        388,
        760,
        336
      ],
      "dealer_daily": [
        31,
        26,
        -42,
        6,
        18,
        5
      ]
    },
    {
      "code": "3653",
      "name": "健策",
      "market": "TWSE",
      "foreign_daily": [
        -92,
        253,
        824,
        318,
        -82,
        188
      ],
      "dealer_daily": [
        5,
        2,
        -17,
        11,
        7,
        8
      ]
    },
    {
      "code": "1515",
      "name": "力山",
      "market": "TWSE",
      "foreign_daily": [
        -304,
        814,
        -580,
        -601,
        449,
        1599
      ],
      "dealer_daily": [
        -1,
        9,
        -8,
        6,
        10,
        2
      ]
    },
    {
      "code": "2467",
      "name": "志聖",
      "market": "TWSE",
      "foreign_daily": [
        -22,
        14,
        8,
        0,
        802,
        573
      ],
      "dealer_daily": [
        8,
        -6,
        -17,
        0,
        45,
        55
      ]
    },
    {
      "code": "3030",
      "name": "德律",
      "market": "TWSE",
      "foreign_daily": [
        34,
        -113,
        467,
        306,
        334,
        344
      ],
      "dealer_daily": [
        5,
        -3,
        -58,
        31,
        -3,
        138
      ]
    },
    {
      "code": "6224",
      "name": "聚鼎",
      "market": "TWSE",
      "foreign_daily": [
        55,
        -12,
        -30,
        226,
        124,
        1003
      ],
      "dealer_daily": [
        1,
        1,
        0,
        -1,
        5,
        -1
      ]
    },
    {
      "code": "4105",
      "name": "東洋",
      "market": "TPEX",
      "foreign_daily": [
        532,
        301,
        175,
        469,
        -7,
        -126
      ],
      "dealer_daily": [
        0,
        3,
        -2,
        5,
        0,
        -1
      ]
    },
    {
      "code": "3017",
      "name": "奇鋐",
      "market": "TWSE",
      "foreign_daily": [
        862,
        -345,
        -2054,
        312,
        1694,
        871
      ],
      "dealer_daily": [
        57,
        -24,
        -127,
        20,
        58,
        52
      ]
    },
    {
      "code": "2049",
      "name": "上銀",
      "market": "TWSE",
      "foreign_daily": [
        124,
        33,
        -579,
        597,
        173,
        956
      ],
      "dealer_daily": [
        -42,
        -49,
        -46,
        75,
        89,
        173
      ]
    },
    {
      "code": "4916",
      "name": "事欣科",
      "market": "TWSE",
      "foreign_daily": [
        15,
        -147,
        -107,
        -556,
        537,
        1551
      ],
      "dealer_daily": [
        4,
        -23,
        -35,
        9,
        72,
        106
      ]
    },
    {
      "code": "6141",
      "name": "柏承",
      "market": "TWSE",
      "foreign_daily": [
        672,
        731,
        -26,
        -31,
        -57,
        -23
      ],
      "dealer_daily": [
        14,
        -1,
        -13,
        0,
        1,
        0
      ]
    },
    {
      "code": "6191",
      "name": "精成科",
      "market": "TWSE",
      "foreign_daily": [
        -855,
        -347,
        6981,
        483,
        -1613,
        -3395
      ],
      "dealer_daily": [
        -43,
        -28,
        153,
        103,
        207,
        -190
      ]
    },
    {
      "code": "6186",
      "name": "新潤",
      "market": "TPEX",
      "foreign_daily": [
        76,
        534,
        -26,
        -28,
        193,
        453
      ],
      "dealer_daily": [
        2,
        29,
        -1,
        0,
        1,
        4
      ]
    },
    {
      "code": "7795",
      "name": "長廣",
      "market": "TWSE",
      "foreign_daily": [
        -12,
        -17,
        206,
        -78,
        238,
        850
      ],
      "dealer_daily": [
        -5,
        -1,
        46,
        -19,
        9,
        -24
      ]
    },
    {
      "code": "5328",
      "name": "華容",
      "market": "TPEX",
      "foreign_daily": [
        -2637,
        2765,
        3738,
        2690,
        -3996,
        -1390
      ],
      "dealer_daily": [
        140,
        125,
        249,
        -452,
        91,
        -44
      ]
    },
    {
      "code": "3501",
      "name": "維熹",
      "market": "TWSE",
      "foreign_daily": [
        368,
        14,
        -295,
        203,
        860,
        -11
      ],
      "dealer_daily": [
        -1,
        0,
        4,
        0,
        0,
        0
      ]
    },
    {
      "code": "6438",
      "name": "迅得",
      "market": "TWSE",
      "foreign_daily": [
        49,
        -10,
        31,
        99,
        178,
        767
      ],
      "dealer_daily": [
        1,
        -9,
        -54,
        14,
        47,
        104
      ]
    },
    {
      "code": "2404",
      "name": "漢唐",
      "market": "TWSE",
      "foreign_daily": [
        -19,
        777,
        365,
        -484,
        -435,
        845
      ],
      "dealer_daily": [
        -8,
        67,
        -95,
        0,
        36,
        16
      ]
    },
    {
      "code": "5228",
      "name": "鈺鎧",
      "market": "TPEX",
      "foreign_daily": [
        -68,
        -114,
        46,
        67,
        164,
        927
      ],
      "dealer_daily": [
        0,
        0,
        0,
        0,
        -8,
        9
      ]
    },
    {
      "code": "2345",
      "name": "智邦",
      "market": "TWSE",
      "foreign_daily": [
        -222,
        -310,
        700,
        -196,
        314,
        718
      ],
      "dealer_daily": [
        3,
        74,
        -101,
        36,
        21,
        90
      ]
    },
    {
      "code": "2537",
      "name": "聯上發",
      "market": "TWSE",
      "foreign_daily": [
        79,
        402,
        862,
        -152,
        -63,
        -153
      ],
      "dealer_daily": [
        17,
        -22,
        17,
        15,
        0,
        1
      ]
    },
    {
      "code": "1904",
      "name": "正隆",
      "market": "TWSE",
      "foreign_daily": [
        535,
        -119,
        583,
        300,
        -10,
        -345
      ],
      "dealer_daily": [
        7,
        0,
        -11,
        9,
        12,
        8
      ]
    },
    {
      "code": "8996",
      "name": "高力",
      "market": "TWSE",
      "foreign_daily": [
        -128,
        17,
        420,
        253,
        148,
        178
      ],
      "dealer_daily": [
        20,
        -13,
        40,
        -20,
        -7,
        3
      ]
    },
    {
      "code": "1310",
      "name": "台苯",
      "market": "TWSE",
      "foreign_daily": [
        -682,
        -526,
        -39,
        -733,
        3134,
        -296
      ],
      "dealer_daily": [
        11,
        18,
        45,
        -17,
        -28,
        19
      ]
    },
    {
      "code": "2305",
      "name": "全友",
      "market": "TWSE",
      "foreign_daily": [
        169,
        -100,
        574,
        111,
        15,
        81
      ],
      "dealer_daily": [
        -7,
        1,
        187,
        -23,
        -25,
        -8
      ]
    },
    {
      "code": "4306",
      "name": "炎洲",
      "market": "TWSE",
      "foreign_daily": [
        253,
        768,
        590,
        -434,
        -315,
        -27
      ],
      "dealer_daily": [
        7,
        1,
        -8,
        0,
        0,
        8
      ]
    },
    {
      "code": "2360",
      "name": "致茂",
      "market": "TWSE",
      "foreign_daily": [
        516,
        260,
        115,
        67,
        19,
        -164
      ],
      "dealer_daily": [
        31,
        4,
        -10,
        1,
        -14,
        23
      ]
    },
    {
      "code": "3090",
      "name": "日電貿",
      "market": "TWSE",
      "foreign_daily": [
        336,
        440,
        -77,
        -47,
        78,
        74
      ],
      "dealer_daily": [
        75,
        -42,
        -17,
        6,
        -7,
        1
      ]
    },
    {
      "code": "1597",
      "name": "直得",
      "market": "TWSE",
      "foreign_daily": [
        168,
        160,
        43,
        265,
        276,
        -108
      ],
      "dealer_daily": [
        15,
        6,
        -61,
        -15,
        54,
        17
      ]
    },
    {
      "code": "6491",
      "name": "晶碩",
      "market": "TWSE",
      "foreign_daily": [
        227,
        18,
        40,
        283,
        304,
        -74
      ],
      "dealer_daily": [
        0,
        -3,
        1,
        2,
        11,
        0
      ]
    },
    {
      "code": "6409",
      "name": "旭隼",
      "market": "TWSE",
      "foreign_daily": [
        -11,
        818,
        -162,
        -184,
        44,
        288
      ],
      "dealer_daily": [
        4,
        105,
        -77,
        11,
        4,
        -35
      ]
    },
    {
      "code": "6909",
      "name": "創控",
      "market": "TWSE",
      "foreign_daily": [
        924,
        -453,
        176,
        -140,
        -85,
        365
      ],
      "dealer_daily": [
        -13,
        0,
        0,
        0,
        0,
        15
      ]
    },
    {
      "code": "4162",
      "name": "智擎",
      "market": "TPEX",
      "foreign_daily": [
        228,
        -68,
        43,
        92,
        247,
        244
      ],
      "dealer_daily": [
        7,
        0,
        1,
        4,
        3,
        1
      ]
    },
    {
      "code": "2204",
      "name": "中華",
      "market": "TWSE",
      "foreign_daily": [
        232,
        65,
        -336,
        327,
        -130,
        606
      ],
      "dealer_daily": [
        -2,
        10,
        2,
        6,
        34,
        15
      ]
    },
    {
      "code": "2836",
      "name": "高雄銀",
      "market": "TWSE",
      "foreign_daily": [
        366,
        862,
        309,
        135,
        -658,
        -267
      ],
      "dealer_daily": [
        -3,
        24,
        -12,
        6,
        -6,
        -1
      ]
    },
    {
      "code": "7827",
      "name": "漢康-KY創",
      "market": "TWSE",
      "foreign_daily": [
        86,
        212,
        221,
        41,
        194,
        -30
      ],
      "dealer_daily": [
        2,
        -2,
        2,
        2,
        0,
        5
      ]
    },
    {
      "code": "4746",
      "name": "台耀",
      "market": "TWSE",
      "foreign_daily": [
        226,
        -275,
        -310,
        437,
        393,
        221
      ],
      "dealer_daily": [
        3,
        0,
        -5,
        13,
        3,
        6
      ]
    },
    {
      "code": "2480",
      "name": "敦陽科",
      "market": "TWSE",
      "foreign_daily": [
        42,
        31,
        460,
        -265,
        328,
        65
      ],
      "dealer_daily": [
        0,
        0,
        0,
        1,
        -2,
        6
      ]
    },
    {
      "code": "3092",
      "name": "鴻碩",
      "market": "TWSE",
      "foreign_daily": [
        -84,
        -22,
        37,
        -166,
        40,
        796
      ],
      "dealer_daily": [
        0,
        0,
        -1,
        0,
        0,
        3
      ]
    },
    {
      "code": "6488",
      "name": "環球晶",
      "market": "TPEX",
      "foreign_daily": [
        -474,
        171,
        -29,
        38,
        489,
        400
      ],
      "dealer_daily": [
        228,
        33,
        -179,
        344,
        299,
        -18
      ]
    },
    {
      "code": "1604",
      "name": "聲寶",
      "market": "TWSE",
      "foreign_daily": [
        203,
        200,
        -85,
        94,
        80,
        101
      ],
      "dealer_daily": [
        1,
        9,
        -2,
        1,
        -1,
        2
      ]
    },
    {
      "code": "1702",
      "name": "南僑",
      "market": "TWSE",
      "foreign_daily": [
        199,
        143,
        -88,
        123,
        100,
        87
      ],
      "dealer_daily": [
        -2,
        7,
        3,
        1,
        -1,
        -3
      ]
    },
    {
      "code": "9921",
      "name": "巨大",
      "market": "TWSE",
      "foreign_daily": [
        -56,
        456,
        957,
        -683,
        289,
        -419
      ],
      "dealer_daily": [
        9,
        3,
        0,
        -2,
        -2,
        2
      ]
    },
    {
      "code": "6449",
      "name": "鈺邦",
      "market": "TWSE",
      "foreign_daily": [
        357,
        -85,
        1129,
        240,
        -780,
        -327
      ],
      "dealer_daily": [
        -5,
        -23,
        -7,
        -17,
        44,
        10
      ]
    },
    {
      "code": "6196",
      "name": "帆宣",
      "market": "TWSE",
      "foreign_daily": [
        -165,
        295,
        -342,
        -13,
        455,
        283
      ],
      "dealer_daily": [
        17,
        16,
        -34,
        3,
        71,
        42
      ]
    },
    {
      "code": "3093",
      "name": "港建*",
      "market": "TPEX",
      "foreign_daily": [
        -766,
        21,
        115,
        -142,
        -21,
        1305
      ],
      "dealer_daily": [
        38,
        0,
        2,
        -10,
        -3,
        145
      ]
    },
    {
      "code": "4540",
      "name": "全球傳動",
      "market": "TWSE",
      "foreign_daily": [
        -45,
        -48,
        242,
        131,
        236,
        -5
      ],
      "dealer_daily": [
        0,
        3,
        -1,
        0,
        4,
        0
      ]
    },
    {
      "code": "6164",
      "name": "華興",
      "market": "TWSE",
      "foreign_daily": [
        -125,
        -440,
        124,
        -19,
        312,
        658
      ],
      "dealer_daily": [
        0,
        0,
        0,
        0,
        0,
        19
      ]
    },
    {
      "code": "6129",
      "name": "普誠",
      "market": "TPEX",
      "foreign_daily": [
        92,
        -611,
        581,
        98,
        192,
        154
      ],
      "dealer_daily": [
        25,
        -24,
        0,
        0,
        0,
        0
      ]
    },
    {
      "code": "4155",
      "name": "訊映",
      "market": "TWSE",
      "foreign_daily": [
        119,
        -27,
        71,
        37,
        195,
        110
      ],
      "dealer_daily": [
        3,
        0,
        -1,
        0,
        0,
        0
      ]
    },
    {
      "code": "6190",
      "name": "萬泰科",
      "market": "TPEX",
      "foreign_daily": [
        137,
        -255,
        -412,
        -729,
        1297,
        458
      ],
      "dealer_daily": [
        28,
        -14,
        21,
        -29,
        125,
        126
      ]
    },
    {
      "code": "4991",
      "name": "環宇-KY",
      "market": "TPEX",
      "foreign_daily": [
        189,
        93,
        -169,
        185,
        76,
        65
      ],
      "dealer_daily": [
        13,
        12,
        30,
        64,
        -2,
        40
      ]
    },
    {
      "code": "3490",
      "name": "單井",
      "market": "TPEX",
      "foreign_daily": [
        -29,
        39,
        118,
        56,
        63,
        187
      ],
      "dealer_daily": [
        0,
        1,
        0,
        0,
        0,
        1
      ]
    },
    {
      "code": "1721",
      "name": "三晃",
      "market": "TWSE",
      "foreign_daily": [
        -295,
        -210,
        320,
        -118,
        118,
        597
      ],
      "dealer_daily": [
        -3,
        0,
        2,
        0,
        0,
        6
      ]
    },
    {
      "code": "1789",
      "name": "神隆",
      "market": "TWSE",
      "foreign_daily": [
        276,
        17,
        -148,
        325,
        -79,
        18
      ],
      "dealer_daily": [
        -4,
        0,
        -6,
        9,
        5,
        0
      ]
    },
    {
      "code": "8027",
      "name": "鈦昇",
      "market": "TPEX",
      "foreign_daily": [
        117,
        69,
        16,
        147,
        -4,
        64
      ],
      "dealer_daily": [
        1,
        58,
        -10,
        13,
        2,
        6
      ]
    },
    {
      "code": "2442",
      "name": "新美齊",
      "market": "TWSE",
      "foreign_daily": [
        -69,
        -103,
        -194,
        459,
        136,
        173
      ],
      "dealer_daily": [
        0,
        -1,
        3,
        0,
        -1,
        0
      ]
    },
    {
      "code": "3694",
      "name": "海華",
      "market": "TWSE",
      "foreign_daily": [
        -143,
        -42,
        -446,
        -29,
        178,
        876
      ],
      "dealer_daily": [
        -1,
        -3,
        0,
        -7,
        15,
        4
      ]
    },
    {
      "code": "3416",
      "name": "融程電",
      "market": "TWSE",
      "foreign_daily": [
        6,
        69,
        -189,
        7,
        -13,
        512
      ],
      "dealer_daily": [
        -4,
        -6,
        -18,
        -3,
        27,
        59
      ]
    },
    {
      "code": "6658",
      "name": "聯策",
      "market": "TWSE",
      "foreign_daily": [
        -12,
        -2,
        -494,
        -31,
        687,
        233
      ],
      "dealer_daily": [
        0,
        16,
        -16,
        0,
        35,
        19
      ]
    },
    {
      "code": "3546",
      "name": "宇峻",
      "market": "TPEX",
      "foreign_daily": [
        103,
        61,
        50,
        69,
        105,
        -7
      ],
      "dealer_daily": [
        9,
        -7,
        6,
        -2,
        3,
        -1
      ]
    },
    {
      "code": "4707",
      "name": "磐亞",
      "market": "TPEX",
      "foreign_daily": [
        511,
        86,
        -659,
        -289,
        946,
        -217
      ],
      "dealer_daily": [
        123,
        62,
        2,
        261,
        -34,
        -23
      ]
    },
    {
      "code": "5519",
      "name": "隆大",
      "market": "TWSE",
      "foreign_daily": [
        34,
        150,
        334,
        -50,
        -19,
        -72
      ],
      "dealer_daily": [
        116,
        146,
        -1,
        11,
        71,
        -2
      ]
    },
    {
      "code": "5222",
      "name": "全訊",
      "market": "TWSE",
      "foreign_daily": [
        -111,
        -17,
        -71,
        -49,
        448,
        175
      ],
      "dealer_daily": [
        3,
        -5,
        -2,
        4,
        5,
        2
      ]
    },
    {
      "code": "5213",
      "name": "亞昕",
      "market": "TPEX",
      "foreign_daily": [
        117,
        45,
        -27,
        112,
        -39,
        151
      ],
      "dealer_daily": [
        0,
        0,
        0,
        0,
        0,
        1
      ]
    },
    {
      "code": "8462",
      "name": "柏文",
      "market": "TWSE",
      "foreign_daily": [
        2,
        42,
        78,
        190,
        11,
        21
      ],
      "dealer_daily": [
        0,
        1,
        2,
        0,
        0,
        0
      ]
    },
    {
      "code": "4536",
      "name": "拓凱",
      "market": "TWSE",
      "foreign_daily": [
        60,
        152,
        -33,
        50,
        17,
        76
      ],
      "dealer_daily": [
        1,
        -1,
        0,
        0,
        62,
        3
      ]
    },
    {
      "code": "2461",
      "name": "光群雷",
      "market": "TWSE",
      "foreign_daily": [
        -79,
        -91,
        120,
        149,
        296,
        -75
      ],
      "dealer_daily": [
        0,
        0,
        3,
        0,
        0,
        1
      ]
    },
    {
      "code": "2236",
      "name": "百達-KY",
      "market": "TWSE",
      "foreign_daily": [
        7,
        34,
        464,
        18,
        -292,
        87
      ],
      "dealer_daily": [
        0,
        -1,
        -1,
        0,
        0,
        3
      ]
    },
    {
      "code": "6873",
      "name": "泓德能源",
      "market": "TWSE",
      "foreign_daily": [
        95,
        17,
        -108,
        198,
        7,
        107
      ],
      "dealer_daily": [
        7,
        1,
        -5,
        2,
        -2,
        -1
      ]
    },
    {
      "code": "6712",
      "name": "長聖",
      "market": "TPEX",
      "foreign_daily": [
        353,
        7,
        -121,
        113,
        -47,
        8
      ],
      "dealer_daily": [
        8,
        -3,
        2,
        1,
        -4,
        -1
      ]
    },
    {
      "code": "5278",
      "name": "尚凡*",
      "market": "TPEX",
      "foreign_daily": [
        39,
        13,
        169,
        -54,
        94,
        45
      ],
      "dealer_daily": [
        -1,
        0,
        4,
        0,
        0,
        0
      ]
    },
    {
      "code": "5284",
      "name": "jpp-KY",
      "market": "TWSE",
      "foreign_daily": [
        -30,
        -33,
        48,
        122,
        175,
        7
      ],
      "dealer_daily": [
        3,
        -12,
        -6,
        51,
        47,
        -27
      ]
    },
    {
      "code": "2727",
      "name": "王品",
      "market": "TWSE",
      "foreign_daily": [
        126,
        182,
        -57,
        151,
        -179,
        59
      ],
      "dealer_daily": [
        0,
        93,
        1,
        1,
        20,
        27
      ]
    },
    {
      "code": "3346",
      "name": "麗清",
      "market": "TWSE",
      "foreign_daily": [
        118,
        -307,
        180,
        260,
        923,
        -894
      ],
      "dealer_daily": [
        1,
        2,
        -1,
        -1,
        14,
        -12
      ]
    },
    {
      "code": "1447",
      "name": "力鵬",
      "market": "TWSE",
      "foreign_daily": [
        -181,
        -84,
        781,
        -25,
        -151,
        -60
      ],
      "dealer_daily": [
        0,
        2,
        -11,
        15,
        561,
        49
      ]
    },
    {
      "code": "6167",
      "name": "久正",
      "market": "TPEX",
      "foreign_daily": [
        -63,
        -25,
        21,
        -161,
        466,
        41
      ],
      "dealer_daily": [
        0,
        0,
        0,
        0,
        0,
        1
      ]
    },
    {
      "code": "6588",
      "name": "東典光電",
      "market": "TPEX",
      "foreign_daily": [
        -76,
        -92,
        113,
        385,
        -63,
        8
      ],
      "dealer_daily": [
        0,
        1,
        -1,
        1,
        0,
        1
      ]
    },
    {
      "code": "2417",
      "name": "圓剛",
      "market": "TWSE",
      "foreign_daily": [
        -30,
        10,
        -63,
        161,
        175,
        11
      ],
      "dealer_daily": [
        0,
        -1,
        3,
        0,
        0,
        -1
      ]
    },
    {
      "code": "2107",
      "name": "厚生",
      "market": "TWSE",
      "foreign_daily": [
        295,
        157,
        -143,
        -41,
        -39,
        32
      ],
      "dealer_daily": [
        6,
        7,
        -3,
        0,
        0,
        -7
      ]
    },
    {
      "code": "2707",
      "name": "晶華",
      "market": "TWSE",
      "foreign_daily": [
        102,
        93,
        18,
        109,
        -95,
        13
      ],
      "dealer_daily": [
        16,
        9,
        -1,
        4,
        2,
        -1
      ]
    },
    {
      "code": "8936",
      "name": "國統",
      "market": "TPEX",
      "foreign_daily": [
        39,
        844,
        -255,
        111,
        3705,
        -4210
      ],
      "dealer_daily": [
        0,
        0,
        1,
        6,
        14,
        27
      ]
    },
    {
      "code": "9940",
      "name": "信義",
      "market": "TWSE",
      "foreign_daily": [
        164,
        25,
        72,
        49,
        -158,
        81
      ],
      "dealer_daily": [
        40,
        8,
        9,
        9,
        19,
        8
      ]
    },
    {
      "code": "6517",
      "name": "保勝光學",
      "market": "TPEX",
      "foreign_daily": [
        1,
        142,
        3,
        40,
        178,
        -138
      ],
      "dealer_daily": [
        -1,
        1,
        0,
        -1,
        2,
        13
      ]
    },
    {
      "code": "1467",
      "name": "南緯",
      "market": "TWSE",
      "foreign_daily": [
        8,
        -16,
        -37,
        59,
        -31,
        242
      ],
      "dealer_daily": [
        0,
        0,
        1,
        -5,
        0,
        6
      ]
    },
    {
      "code": "3217",
      "name": "優群",
      "market": "TPEX",
      "foreign_daily": [
        232,
        838,
        -34,
        -216,
        -230,
        -371
      ],
      "dealer_daily": [
        9,
        296,
        73,
        -17,
        -4,
        -6
      ]
    },
    {
      "code": "6492",
      "name": "生華科",
      "market": "TPEX",
      "foreign_daily": [
        31,
        46,
        2,
        27,
        89,
        24
      ],
      "dealer_daily": [
        0,
        0,
        0,
        0,
        1,
        0
      ]
    },
    {
      "code": "2748",
      "name": "雲品",
      "market": "TWSE",
      "foreign_daily": [
        50,
        40,
        76,
        39,
        -9,
        22
      ],
      "dealer_daily": [
        -1,
        0,
        2,
        0,
        0,
        0
      ]
    },
    {
      "code": "6510",
      "name": "精測",
      "market": "TPEX",
      "foreign_daily": [
        -4,
        -4,
        -44,
        35,
        202,
        32
      ],
      "dealer_daily": [
        5,
        5,
        -13,
        1,
        29,
        -5
      ]
    },
    {
      "code": "6841",
      "name": "長佳智能",
      "market": "TPEX",
      "foreign_daily": [
        56,
        -1,
        -39,
        110,
        25,
        60
      ],
      "dealer_daily": [
        4,
        -1,
        -3,
        4,
        2,
        -1
      ]
    },
    {
      "code": "7803",
      "name": "雲象科技-創",
      "market": "TWSE",
      "foreign_daily": [
        38,
        16,
        43,
        58,
        1,
        54
      ],
      "dealer_daily": [
        0,
        0,
        0,
        0,
        0,
        5
      ]
    },
    {
      "code": "4113",
      "name": "聯上",
      "market": "TPEX",
      "foreign_daily": [
        4,
        -27,
        46,
        25,
        -53,
        215
      ],
      "dealer_daily": [
        0,
        0,
        0,
        0,
        0,
        1
      ]
    },
    {
      "code": "6233",
      "name": "旺玖",
      "market": "TPEX",
      "foreign_daily": [
        236,
        -185,
        187,
        -63,
        16,
        9
      ],
      "dealer_daily": [
        0,
        0,
        0,
        0,
        0,
        1
      ]
    },
    {
      "code": "6789",
      "name": "采鈺",
      "market": "TWSE",
      "foreign_daily": [
        -292,
        81,
        110,
        63,
        85,
        149
      ],
      "dealer_daily": [
        25,
        30,
        -99,
        -8,
        24,
        41
      ]
    },
    {
      "code": "6175",
      "name": "立敦",
      "market": "TPEX",
      "foreign_daily": [
        248,
        -983,
        868,
        -333,
        -269,
        665
      ],
      "dealer_daily": [
        256,
        145,
        -118,
        -253,
        134,
        -76
      ]
    },
    {
      "code": "3587",
      "name": "閎康",
      "market": "TPEX",
      "foreign_daily": [
        43,
        -76,
        23,
        170,
        -101,
        135
      ],
      "dealer_daily": [
        -2,
        -20,
        -20,
        -5,
        14,
        42
      ]
    },
    {
      "code": "3066",
      "name": "李洲",
      "market": "TPEX",
      "foreign_daily": [
        -241,
        -34,
        50,
        412,
        -37,
        32
      ],
      "dealer_daily": [
        -11,
        -1,
        36,
        1,
        -1,
        -19
      ]
    },
    {
      "code": "2061",
      "name": "風青",
      "market": "TPEX",
      "foreign_daily": [
        1,
        -35,
        45,
        47,
        25,
        96
      ],
      "dealer_daily": [
        -4,
        0,
        0,
        0,
        132,
        -5
      ]
    },
    {
      "code": "3055",
      "name": "蔚華科",
      "market": "TWSE",
      "foreign_daily": [
        315,
        -903,
        53,
        -12,
        -116,
        832
      ],
      "dealer_daily": [
        74,
        -45,
        -18,
        43,
        19,
        109
      ]
    },
    {
      "code": "2506",
      "name": "太設",
      "market": "TWSE",
      "foreign_daily": [
        27,
        4,
        12,
        45,
        77,
        -3
      ],
      "dealer_daily": [
        0,
        4,
        -2,
        0,
        0,
        0
      ]
    },
    {
      "code": "6122",
      "name": "擎邦",
      "market": "TPEX",
      "foreign_daily": [
        31,
        58,
        -46,
        -16,
        44,
        91
      ],
      "dealer_daily": [
        9,
        1,
        -4,
        0,
        2,
        4
      ]
    },
    {
      "code": "6535",
      "name": "順藥",
      "market": "TPEX",
      "foreign_daily": [
        46,
        -43,
        -18,
        86,
        48,
        40
      ],
      "dealer_daily": [
        0,
        0,
        1,
        0,
        0,
        0
      ]
    },
    {
      "code": "7402",
      "name": "邑錡",
      "market": "TPEX",
      "foreign_daily": [
        -3,
        -15,
        -11,
        -2,
        -289,
        479
      ],
      "dealer_daily": [
        2,
        10,
        1,
        5,
        65,
        11
      ]
    },
    {
      "code": "2745",
      "name": "五福",
      "market": "TPEX",
      "foreign_daily": [
        15,
        117,
        56,
        -28,
        -32,
        30
      ],
      "dealer_daily": [
        1,
        63,
        38,
        -1,
        59,
        68
      ]
    },
    {
      "code": "6243",
      "name": "迅杰",
      "market": "TWSE",
      "foreign_daily": [
        -8,
        250,
        -65,
        -20,
        -1,
        -2
      ],
      "dealer_daily": [
        4,
        -4,
        0,
        0,
        1,
        0
      ]
    },
    {
      "code": "1587",
      "name": "吉茂",
      "market": "TWSE",
      "foreign_daily": [
        -27,
        28,
        -23,
        133,
        -28,
        66
      ],
      "dealer_daily": [
        2,
        2,
        -5,
        -1,
        2,
        2
      ]
    },
    {
      "code": "1760",
      "name": "寶齡富錦",
      "market": "TWSE",
      "foreign_daily": [
        22,
        -19,
        -42,
        40,
        60,
        85
      ],
      "dealer_daily": [
        0,
        1,
        -2,
        0,
        1,
        1
      ]
    },
    {
      "code": "6199",
      "name": "天品",
      "market": "TPEX",
      "foreign_daily": [
        32,
        -76,
        -2,
        -33,
        232,
        -14
      ],
      "dealer_daily": [
        25,
        -14,
        0,
        0,
        0,
        -1
      ]
    },
    {
      "code": "4949",
      "name": "有成精密",
      "market": "TWSE",
      "foreign_daily": [
        74,
        -250,
        -21,
        207,
        -28,
        155
      ],
      "dealer_daily": [
        -3,
        -1,
        -1,
        0,
        2,
        4
      ]
    },
    {
      "code": "6579",
      "name": "研揚",
      "market": "TWSE",
      "foreign_daily": [
        35,
        4,
        -1,
        62,
        54,
        -20
      ],
      "dealer_daily": [
        -4,
        -1,
        9,
        0,
        -2,
        0
      ]
    },
    {
      "code": "6664",
      "name": "群翊",
      "market": "TPEX",
      "foreign_daily": [
        38,
        -1,
        -104,
        163,
        6,
        31
      ],
      "dealer_daily": [
        10,
        2,
        -14,
        5,
        27,
        14
      ]
    },
    {
      "code": "7703",
      "name": "銳澤",
      "market": "TPEX",
      "foreign_daily": [
        50,
        218,
        -99,
        -41,
        21,
        -22
      ],
      "dealer_daily": [
        0,
        0,
        0,
        0,
        0,
        1
      ]
    },
    {
      "code": "6261",
      "name": "久元",
      "market": "TPEX",
      "foreign_daily": [
        -113,
        -470,
        359,
        166,
        27,
        155
      ],
      "dealer_daily": [
        197,
        18,
        125,
        20,
        14,
        2
      ]
    },
    {
      "code": "5478",
      "name": "智冠",
      "market": "TPEX",
      "foreign_daily": [
        19,
        41,
        -5,
        42,
        28,
        -4
      ],
      "dealer_daily": [
        2,
        0,
        -1,
        0,
        0,
        5
      ]
    },
    {
      "code": "1616",
      "name": "億泰",
      "market": "TWSE",
      "foreign_daily": [
        22,
        -27,
        -66,
        115,
        153,
        -79
      ],
      "dealer_daily": [
        1,
        114,
        11,
        25,
        0,
        0
      ]
    },
    {
      "code": "8176",
      "name": "智捷",
      "market": "TPEX",
      "foreign_daily": [
        -10,
        1,
        -49,
        -74,
        36,
        212
      ],
      "dealer_daily": [
        0,
        0,
        0,
        0,
        0,
        4
      ]
    },
    {
      "code": "5225",
      "name": "東科-KY",
      "market": "TWSE",
      "foreign_daily": [
        50,
        52,
        -59,
        -13,
        49,
        36
      ],
      "dealer_daily": [
        -1,
        0,
        4,
        -1,
        1,
        2
      ]
    },
    {
      "code": "2433",
      "name": "互盛電",
      "market": "TWSE",
      "foreign_daily": [
        45,
        -10,
        -21,
        5,
        17,
        79
      ],
      "dealer_daily": [
        0,
        1,
        1,
        0,
        0,
        2
      ]
    },
    {
      "code": "2849",
      "name": "安泰銀",
      "market": "TWSE",
      "foreign_daily": [
        25,
        57,
        -93,
        65,
        29,
        30
      ],
      "dealer_daily": [
        0,
        24,
        -9,
        0,
        0,
        -2
      ]
    },
    {
      "code": "6241",
      "name": "鑫永洋",
      "market": "TPEX",
      "foreign_daily": [
        52,
        27,
        -2,
        7,
        19,
        5
      ],
      "dealer_daily": [
        0,
        0,
        0,
        0,
        0,
        1
      ]
    },
    {
      "code": "8935",
      "name": "邦泰",
      "market": "TPEX",
      "foreign_daily": [
        -29,
        -104,
        29,
        47,
        256,
        -91
      ],
      "dealer_daily": [
        0,
        0,
        0,
        0,
        0,
        1
      ]
    },
    {
      "code": "3611",
      "name": "鼎翰",
      "market": "TPEX",
      "foreign_daily": [
        5,
        4,
        -13,
        -1,
        105,
        7
      ],
      "dealer_daily": [
        0,
        0,
        0,
        0,
        1,
        18
      ]
    },
    {
      "code": "3268",
      "name": "海德威",
      "market": "TPEX",
      "foreign_daily": [
        28,
        -18,
        33,
        20,
        2,
        36
      ],
      "dealer_daily": [
        0,
        0,
        0,
        0,
        0,
        1
      ]
    },
    {
      "code": "3052",
      "name": "夆典",
      "market": "TWSE",
      "foreign_daily": [
        59,
        60,
        -10,
        35,
        -2,
        -42
      ],
      "dealer_daily": [
        8,
        8,
        -9,
        0,
        0,
        10
      ]
    },
    {
      "code": "3686",
      "name": "達能",
      "market": "TWSE",
      "foreign_daily": [
        18,
        66,
        -71,
        5,
        94,
        -17
      ],
      "dealer_daily": [
        0,
        0,
        2,
        0,
        -2,
        2
      ]
    },
    {
      "code": "6146",
      "name": "耕興",
      "market": "TPEX",
      "foreign_daily": [
        46,
        117,
        22,
        -21,
        -73,
        2
      ],
      "dealer_daily": [
        -2,
        17,
        -1,
        -10,
        -1,
        -2
      ]
    },
    {
      "code": "6763",
      "name": "綠界科技*",
      "market": "TPEX",
      "foreign_daily": [
        -2,
        -43,
        -98,
        49,
        326,
        -139
      ],
      "dealer_daily": [
        1,
        14,
        -1,
        1,
        5,
        -1
      ]
    },
    {
      "code": "3529",
      "name": "力旺",
      "market": "TPEX",
      "foreign_daily": [
        -89,
        209,
        -74,
        33,
        17,
        -11
      ],
      "dealer_daily": [
        3,
        -4,
        22,
        4,
        14,
        -6
      ]
    },
    {
      "code": "8916",
      "name": "光隆",
      "market": "TPEX",
      "foreign_daily": [
        0,
        8,
        75,
        5,
        25,
        -28
      ],
      "dealer_daily": [
        -17,
        0,
        0,
        5,
        16,
        10
      ]
    },
    {
      "code": "1735",
      "name": "日勝化",
      "market": "TWSE",
      "foreign_daily": [
        76,
        -8,
        -62,
        25,
        9,
        44
      ],
      "dealer_daily": [
        0,
        0,
        3,
        -3,
        2,
        -1
      ]
    },
    {
      "code": "1451",
      "name": "年興",
      "market": "TWSE",
      "foreign_daily": [
        85,
        -22,
        -15,
        0,
        24,
        11
      ],
      "dealer_daily": [
        0,
        7,
        -1,
        0,
        0,
        -5
      ]
    },
    {
      "code": "6931",
      "name": "青松健康",
      "market": "TWSE",
      "foreign_daily": [
        35,
        12,
        -20,
        6,
        16,
        34
      ],
      "dealer_daily": [
        1,
        1,
        0,
        0,
        0,
        -1
      ]
    },
    {
      "code": "3441",
      "name": "聯一光",
      "market": "TPEX",
      "foreign_daily": [
        52,
        201,
        -2,
        -33,
        -54,
        -82
      ],
      "dealer_daily": [
        248,
        12,
        -125,
        -11,
        -3,
        -4
      ]
    },
    {
      "code": "2059",
      "name": "川湖",
      "market": "TWSE",
      "foreign_daily": [
        73,
        127,
        22,
        6,
        -68,
        -79
      ],
      "dealer_daily": [
        10,
        1,
        6,
        -5,
        -13,
        7
      ]
    },
    {
      "code": "2017",
      "name": "官田鋼",
      "market": "TWSE",
      "foreign_daily": [
        14,
        -24,
        -3,
        62,
        -80,
        112
      ],
      "dealer_daily": [
        2,
        0,
        2,
        2,
        -1,
        -4
      ]
    },
    {
      "code": "3520",
      "name": "華盈",
      "market": "TPEX",
      "foreign_daily": [
        48,
        -36,
        35,
        -53,
        86,
        0
      ],
      "dealer_daily": [
        0,
        0,
        0,
        0,
        0,
        3
      ]
    },
    {
      "code": "2390",
      "name": "云辰",
      "market": "TWSE",
      "foreign_daily": [
        65,
        -393,
        -151,
        39,
        330,
        188
      ],
      "dealer_daily": [
        -5,
        0,
        11,
        4,
        0,
        0
      ]
    },
    {
      "code": "6221",
      "name": "晉泰",
      "market": "TPEX",
      "foreign_daily": [
        17,
        -4,
        15,
        11,
        18,
        21
      ],
      "dealer_daily": [
        0,
        0,
        0,
        0,
        0,
        1
      ]
    },
    {
      "code": "6684",
      "name": "安格",
      "market": "TPEX",
      "foreign_daily": [
        139,
        -49,
        -531,
        12,
        -61,
        568
      ],
      "dealer_daily": [
        3,
        0,
        0,
        0,
        0,
        5
      ]
    },
    {
      "code": "5344",
      "name": "立衛",
      "market": "TPEX",
      "foreign_daily": [
        5,
        19,
        2,
        18,
        25,
        5
      ],
      "dealer_daily": [
        0,
        0,
        2,
        0,
        0,
        1
      ]
    },
    {
      "code": "8450",
      "name": "霹靂",
      "market": "TPEX",
      "foreign_daily": [
        29,
        42,
        1,
        0,
        8,
        -8
      ],
      "dealer_daily": [
        0,
        0,
        0,
        3,
        0,
        0
      ]
    },
    {
      "code": "6906",
      "name": "現觀科",
      "market": "TWSE",
      "foreign_daily": [
        59,
        25,
        -26,
        -23,
        12,
        24
      ],
      "dealer_daily": [
        0,
        -1,
        2,
        1,
        -1,
        1
      ]
    },
    {
      "code": "1617",
      "name": "榮星",
      "market": "TWSE",
      "foreign_daily": [
        17,
        4,
        58,
        -6,
        0,
        -2
      ],
      "dealer_daily": [
        0,
        -4,
        -7,
        713,
        1,
        482
      ]
    },
    {
      "code": "5306",
      "name": "桂盟",
      "market": "TWSE",
      "foreign_daily": [
        -1,
        -10,
        20,
        29,
        16,
        17
      ],
      "dealer_daily": [
        1,
        4,
        -2,
        -2,
        0,
        0
      ]
    },
    {
      "code": "2706",
      "name": "第一店",
      "market": "TWSE",
      "foreign_daily": [
        22,
        17,
        -51,
        29,
        4,
        48
      ],
      "dealer_daily": [
        0,
        0,
        12,
        0,
        0,
        -5
      ]
    },
    {
      "code": "4560",
      "name": "強信-KY",
      "market": "TWSE",
      "foreign_daily": [
        3,
        5,
        -19,
        64,
        21,
        -5
      ],
      "dealer_daily": [
        1,
        2,
        0,
        -4,
        1,
        2
      ]
    },
    {
      "code": "8045",
      "name": "達運光電",
      "market": "TWSE",
      "foreign_daily": [
        9,
        3,
        4,
        -8,
        35,
        25
      ],
      "dealer_daily": [
        0,
        0,
        3,
        0,
        0,
        -1
      ]
    },
    {
      "code": "4564",
      "name": "元翎",
      "market": "TWSE",
      "foreign_daily": [
        97,
        50,
        112,
        13,
        183,
        -388
      ],
      "dealer_daily": [
        2,
        1,
        -1,
        0,
        -1,
        1
      ]
    },
    {
      "code": "5353",
      "name": "台林",
      "market": "TPEX",
      "foreign_daily": [
        27,
        54,
        15,
        -67,
        56,
        -19
      ],
      "dealer_daily": [
        0,
        0,
        7,
        0,
        0,
        -2
      ]
    },
    {
      "code": "8042",
      "name": "金山電",
      "market": "TPEX",
      "foreign_daily": [
        192,
        259,
        171,
        -258,
        -22,
        -276
      ],
      "dealer_daily": [
        32,
        71,
        -51,
        0,
        8,
        9
      ]
    },
    {
      "code": "1558",
      "name": "伸興",
      "market": "TWSE",
      "foreign_daily": [
        7,
        13,
        -10,
        16,
        7,
        32
      ],
      "dealer_daily": [
        7,
        0,
        0,
        1,
        -4,
        -2
      ]
    },
    {
      "code": "4438",
      "name": "廣越",
      "market": "TWSE",
      "foreign_daily": [
        24,
        15,
        9,
        15,
        -4,
        5
      ],
      "dealer_daily": [
        0,
        0,
        2,
        0,
        0,
        -1
      ]
    },
    {
      "code": "5263",
      "name": "智崴",
      "market": "TPEX",
      "foreign_daily": [
        98,
        10,
        -56,
        9,
        -1,
        4
      ],
      "dealer_daily": [
        4,
        0,
        5,
        0,
        0,
        0
      ]
    },
    {
      "code": "8038",
      "name": "長園科",
      "market": "TPEX",
      "foreign_daily": [
        51,
        105,
        -130,
        -74,
        53,
        59
      ],
      "dealer_daily": [
        0,
        0,
        1,
        -1,
        1,
        0
      ]
    },
    {
      "code": "6582",
      "name": "申豐",
      "market": "TWSE",
      "foreign_daily": [
        75,
        -20,
        24,
        -14,
        2,
        -5
      ],
      "dealer_daily": [
        1,
        1,
        -1,
        1,
        -1,
        0
      ]
    },
    {
      "code": "1615",
      "name": "大山",
      "market": "TWSE",
      "foreign_daily": [
        38,
        82,
        -70,
        -26,
        11,
        27
      ],
      "dealer_daily": [
        0,
        0,
        6,
        0,
        0,
        0
      ]
    },
    {
      "code": "2397",
      "name": "友通",
      "market": "TWSE",
      "foreign_daily": [
        88,
        -1,
        -216,
        28,
        137,
        25
      ],
      "dealer_daily": [
        0,
        1,
        0,
        0,
        0,
        0
      ]
    },
    {
      "code": "5292",
      "name": "華懋",
      "market": "TWSE",
      "foreign_daily": [
        46,
        28,
        -10,
        -12,
        1,
        8
      ],
      "dealer_daily": [
        -3,
        1,
        -2,
        15,
        6,
        0
      ]
    },
    {
      "code": "6732",
      "name": "昇佳電子",
      "market": "TPEX",
      "foreign_daily": [
        40,
        56,
        -78,
        -15,
        39,
        19
      ],
      "dealer_daily": [
        0,
        0,
        1,
        0,
        0,
        1
      ]
    },
    {
      "code": "3083",
      "name": "網龍",
      "market": "TPEX",
      "foreign_daily": [
        6,
        16,
        13,
        5,
        5,
        15
      ],
      "dealer_daily": [
        0,
        1,
        0,
        0,
        0,
        0
      ]
    },
    {
      "code": "2109",
      "name": "華豐",
      "market": "TWSE",
      "foreign_daily": [
        10,
        -11,
        -42,
        2,
        64,
        36
      ],
      "dealer_daily": [
        0,
        1,
        -2,
        0,
        0,
        2
      ]
    },
    {
      "code": "1603",
      "name": "華電",
      "market": "TWSE",
      "foreign_daily": [
        -9,
        5,
        -181,
        67,
        128,
        49
      ],
      "dealer_daily": [
        4,
        0,
        -5,
        -1,
        46,
        28
      ]
    },
    {
      "code": "4745",
      "name": "合富-KY",
      "market": "TPEX",
      "foreign_daily": [
        15,
        5,
        -8,
        9,
        8,
        29
      ],
      "dealer_daily": [
        0,
        0,
        0,
        0,
        0,
        1
      ]
    },
    {
      "code": "1321",
      "name": "大洋",
      "market": "TWSE",
      "foreign_daily": [
        68,
        -8,
        -41,
        8,
        -34,
        64
      ],
      "dealer_daily": [
        0,
        2,
        12,
        1,
        -1,
        -2
      ]
    },
    {
      "code": "7828",
      "name": "創新服務",
      "market": "TPEX",
      "foreign_daily": [
        8,
        15,
        2,
        8,
        -1,
        25
      ],
      "dealer_daily": [
        2,
        -1,
        -2,
        7,
        -4,
        -1
      ]
    },
    {
      "code": "3530",
      "name": "晶相光",
      "market": "TWSE",
      "foreign_daily": [
        -30,
        21,
        43,
        5,
        11,
        6
      ],
      "dealer_daily": [
        -1,
        1,
        4,
        0,
        0,
        -1
      ]
    },
    {
      "code": "8213",
      "name": "志超",
      "market": "TWSE",
      "foreign_daily": [
        175,
        96,
        -127,
        69,
        164,
        -322
      ],
      "dealer_daily": [
        6,
        0,
        30,
        -2,
        -14,
        -5
      ]
    },
    {
      "code": "1732",
      "name": "毛寶",
      "market": "TWSE",
      "foreign_daily": [
        18,
        16,
        -15,
        12,
        13,
        11
      ],
      "dealer_daily": [
        0,
        0,
        1,
        0,
        0,
        0
      ]
    },
    {
      "code": "4722",
      "name": "國精化",
      "market": "TWSE",
      "foreign_daily": [
        1181,
        -250,
        -138,
        -122,
        -509,
        -108
      ],
      "dealer_daily": [
        62,
        -68,
        -16,
        36,
        13,
        -19
      ]
    },
    {
      "code": "6863",
      "name": "永道-KY",
      "market": "TWSE",
      "foreign_daily": [
        13,
        31,
        -71,
        1,
        59,
        20
      ],
      "dealer_daily": [
        0,
        1,
        8,
        0,
        -5,
        -2
      ]
    },
    {
      "code": "2536",
      "name": "宏普",
      "market": "TWSE",
      "foreign_daily": [
        -31,
        127,
        -57,
        9,
        -57,
        62
      ],
      "dealer_daily": [
        2,
        3,
        -2,
        -1,
        0,
        1
      ]
    },
    {
      "code": "6515",
      "name": "穎崴",
      "market": "TWSE",
      "foreign_daily": [
        -122,
        -68,
        90,
        114,
        46,
        -8
      ],
      "dealer_daily": [
        0,
        4,
        -4,
        -2,
        0,
        15
      ]
    },
    {
      "code": "1586",
      "name": "和勤",
      "market": "TPEX",
      "foreign_daily": [
        -7,
        44,
        45,
        -59,
        -19,
        47
      ],
      "dealer_daily": [
        0,
        0,
        0,
        0,
        0,
        1
      ]
    },
    {
      "code": "3484",
      "name": "崧騰",
      "market": "TPEX",
      "foreign_daily": [
        -146,
        -15,
        58,
        4,
        99,
        51
      ],
      "dealer_daily": [
        1,
        0,
        1,
        1,
        1,
        1
      ]
    },
    {
      "code": "8431",
      "name": "匯鑽科",
      "market": "TPEX",
      "foreign_daily": [
        18,
        -12,
        6,
        19,
        71,
        -53
      ],
      "dealer_daily": [
        -2,
        -1,
        -15,
        -2,
        21,
        9
      ]
    },
    {
      "code": "4588",
      "name": "玖鼎電力",
      "market": "TWSE",
      "foreign_daily": [
        7,
        -7,
        -38,
        -22,
        2,
        104
      ],
      "dealer_daily": [
        0,
        0,
        1,
        -1,
        0,
        1
      ]
    },
    {
      "code": "4173",
      "name": "久裕",
      "market": "TPEX",
      "foreign_daily": [
        -15,
        -4,
        49,
        -31,
        6,
        40
      ],
      "dealer_daily": [
        0,
        0,
        0,
        0,
        0,
        1
      ]
    },
    {
      "code": "4923",
      "name": "力士",
      "market": "TPEX",
      "foreign_daily": [
        -33,
        -28,
        38,
        15,
        39,
        13
      ],
      "dealer_daily": [
        0,
        0,
        120,
        -18,
        -14,
        0
      ]
    },
    {
      "code": "4129",
      "name": "聯合",
      "market": "TPEX",
      "foreign_daily": [
        87,
        9,
        -142,
        51,
        11,
        27
      ],
      "dealer_daily": [
        0,
        0,
        -3,
        5,
        1,
        9
      ]
    },
    {
      "code": "7712",
      "name": "博盛半導體",
      "market": "TPEX",
      "foreign_daily": [
        -193,
        79,
        135,
        75,
        -62,
        9
      ],
      "dealer_daily": [
        33,
        -5,
        -23,
        22,
        -6,
        4
      ]
    },
    {
      "code": "2601",
      "name": "益航",
      "market": "TWSE",
      "foreign_daily": [
        1,
        -368,
        232,
        62,
        217,
        -102
      ],
      "dealer_daily": [
        11,
        2,
        -5,
        0,
        0,
        16
      ]
    },
    {
      "code": "1707",
      "name": "葡萄王",
      "market": "TWSE",
      "foreign_daily": [
        117,
        -121,
        -220,
        447,
        -39,
        -144
      ],
      "dealer_daily": [
        2,
        1,
        -2,
        -4,
        3,
        1
      ]
    },
    {
      "code": "3557",
      "name": "嘉威",
      "market": "TWSE",
      "foreign_daily": [
        13,
        3,
        10,
        18,
        0,
        -5
      ],
      "dealer_daily": [
        1,
        0,
        3,
        0,
        0,
        -1
      ]
    },
    {
      "code": "3675",
      "name": "德微",
      "market": "TPEX",
      "foreign_daily": [
        132,
        -98,
        1,
        0,
        -29,
        33
      ],
      "dealer_daily": [
        -46,
        -4,
        14,
        -3,
        6,
        37
      ]
    },
    {
      "code": "1565",
      "name": "精華",
      "market": "TPEX",
      "foreign_daily": [
        29,
        34,
        -37,
        85,
        -30,
        -43
      ],
      "dealer_daily": [
        0,
        16,
        1,
        4,
        -1,
        -2
      ]
    },
    {
      "code": "3617",
      "name": "碩天",
      "market": "TWSE",
      "foreign_daily": [
        -68,
        263,
        -343,
        91,
        -8,
        102
      ],
      "dealer_daily": [
        -1,
        13,
        -2,
        14,
        3,
        0
      ]
    },
    {
      "code": "6739",
      "name": "竹陞科技",
      "market": "TPEX",
      "foreign_daily": [
        -14,
        -15,
        29,
        52,
        20,
        -36
      ],
      "dealer_daily": [
        2,
        -1,
        -4,
        0,
        2,
        3
      ]
    },
    {
      "code": "3512",
      "name": "皇龍",
      "market": "TPEX",
      "foreign_daily": [
        0,
        2,
        19,
        3,
        15,
        -7
      ],
      "dealer_daily": [
        0,
        0,
        0,
        0,
        0,
        1
      ]
    },
    {
      "code": "5438",
      "name": "東友",
      "market": "TPEX",
      "foreign_daily": [
        60,
        45,
        -37,
        -7,
        -5,
        -26
      ],
      "dealer_daily": [
        1,
        -1,
        0,
        0,
        0,
        1
      ]
    },
    {
      "code": "6461",
      "name": "益得",
      "market": "TPEX",
      "foreign_daily": [
        30,
        13,
        -11,
        -1,
        11,
        -12
      ],
      "dealer_daily": [
        1,
        0,
        0,
        0,
        0,
        0
      ]
    },
    {
      "code": "2516",
      "name": "新建",
      "market": "TWSE",
      "foreign_daily": [
        26,
        -41,
        -7,
        15,
        12,
        24
      ],
      "dealer_daily": [
        0,
        0,
        5,
        0,
        0,
        0
      ]
    },
    {
      "code": "4989",
      "name": "榮科",
      "market": "TWSE",
      "foreign_daily": [
        -706,
        -295,
        -25,
        133,
        -18,
        939
      ],
      "dealer_daily": [
        0,
        -3,
        -1,
        -3,
        19,
        -1
      ]
    },
    {
      "code": "6613",
      "name": "朋億*",
      "market": "TPEX",
      "foreign_daily": [
        3,
        -12,
        11,
        9,
        15,
        2
      ],
      "dealer_daily": [
        -5,
        3,
        -6,
        5,
        11,
        3
      ]
    },
    {
      "code": "2608",
      "name": "嘉里大榮",
      "market": "TWSE",
      "foreign_daily": [
        21,
        36,
        -138,
        33,
        20,
        55
      ],
      "dealer_daily": [
        2,
        9,
        -3,
        1,
        -11,
        5
      ]
    },
    {
      "code": "6914",
      "name": "阜爾運通",
      "market": "TWSE",
      "foreign_daily": [
        9,
        21,
        -13,
        6,
        -3,
        7
      ],
      "dealer_daily": [
        0,
        1,
        3,
        0,
        0,
        -1
      ]
    },
    {
      "code": "6951",
      "name": "青新-創",
      "market": "TWSE",
      "foreign_daily": [
        -6,
        -7,
        10,
        15,
        8,
        7
      ],
      "dealer_daily": [
        -1,
        0,
        3,
        -1,
        1,
        0
      ]
    },
    {
      "code": "5487",
      "name": "通泰",
      "market": "TPEX",
      "foreign_daily": [
        2,
        10,
        10,
        1,
        12,
        -8
      ],
      "dealer_daily": [
        0,
        0,
        0,
        0,
        0,
        1
      ]
    },
    {
      "code": "6903",
      "name": "巨漢",
      "market": "TPEX",
      "foreign_daily": [
        -13,
        152,
        -229,
        124,
        214,
        -221
      ],
      "dealer_daily": [
        5,
        -3,
        -5,
        8,
        70,
        9
      ]
    },
    {
      "code": "4440",
      "name": "宜新實業",
      "market": "TWSE",
      "foreign_daily": [
        -2,
        4,
        -2,
        20,
        1,
        5
      ],
      "dealer_daily": [
        0,
        2,
        0,
        0,
        0,
        1
      ]
    },
    {
      "code": "5299",
      "name": "杰力",
      "market": "TPEX",
      "foreign_daily": [
        96,
        -208,
        69,
        204,
        -274,
        139
      ],
      "dealer_daily": [
        39,
        0,
        0,
        5,
        31,
        2
      ]
    },
    {
      "code": "2211",
      "name": "長榮鋼",
      "market": "TWSE",
      "foreign_daily": [
        148,
        64,
        -69,
        -30,
        -178,
        90
      ],
      "dealer_daily": [
        2,
        5,
        -5,
        1,
        57,
        16
      ]
    },
    {
      "code": "3150",
      "name": "鈺寶-創",
      "market": "TWSE",
      "foreign_daily": [
        3,
        19,
        10,
        1,
        -8,
        0
      ],
      "dealer_daily": [
        7,
        3,
        2,
        2,
        2,
        8
      ]
    },
    {
      "code": "2228",
      "name": "劍麟",
      "market": "TWSE",
      "foreign_daily": [
        19,
        29,
        -30,
        7,
        -20,
        19
      ],
      "dealer_daily": [
        -1,
        1,
        0,
        6,
        4,
        0
      ]
    },
    {
      "code": "5701",
      "name": "劍湖山",
      "market": "TPEX",
      "foreign_daily": [
        -7,
        22,
        4,
        -9,
        11,
        3
      ],
      "dealer_daily": [
        0,
        0,
        0,
        1,
        0,
        1
      ]
    },
    {
      "code": "6195",
      "name": "詩肯",
      "market": "TPEX",
      "foreign_daily": [
        0,
        6,
        -3,
        18,
        3,
        0
      ],
      "dealer_daily": [
        0,
        0,
        1,
        0,
        0,
        0
      ]
    },
    {
      "code": "6486",
      "name": "互動",
      "market": "TPEX",
      "foreign_daily": [
        -10,
        30,
        -26,
        -5,
        16,
        19
      ],
      "dealer_daily": [
        0,
        0,
        1,
        0,
        0,
        0
      ]
    },
    {
      "code": "2910",
      "name": "統領",
      "market": "TWSE",
      "foreign_daily": [
        4,
        0,
        1,
        10,
        6,
        2
      ],
      "dealer_daily": [
        0,
        0,
        1,
        0,
        0,
        0
      ]
    },
    {
      "code": "3135",
      "name": "凌航",
      "market": "TWSE",
      "foreign_daily": [
        -143,
        -305,
        -120,
        204,
        39,
        347
      ],
      "dealer_daily": [
        0,
        24,
        7,
        -5,
        2,
        5
      ]
    },
    {
      "code": "7705",
      "name": "三商餐飲",
      "market": "TWSE",
      "foreign_daily": [
        -12,
        0,
        -8,
        2,
        11,
        26
      ],
      "dealer_daily": [
        8,
        0,
        0,
        0,
        0,
        1
      ]
    },
    {
      "code": "6796",
      "name": "晉弘",
      "market": "TWSE",
      "foreign_daily": [
        -7,
        0,
        7,
        28,
        -8,
        -1
      ],
      "dealer_daily": [
        1,
        0,
        0,
        0,
        0,
        0
      ]
    },
    {
      "code": "5905",
      "name": "南仁湖",
      "market": "TPEX",
      "foreign_daily": [
        1,
        -9,
        -44,
        35,
        84,
        -48
      ],
      "dealer_daily": [
        0,
        0,
        0,
        1,
        0,
        0
      ]
    },
    {
      "code": "4572",
      "name": "駐龍",
      "market": "TWSE",
      "foreign_daily": [
        3,
        -3,
        -6,
        1,
        5,
        17
      ],
      "dealer_daily": [
        0,
        0,
        2,
        0,
        0,
        1
      ]
    },
    {
      "code": "2243",
      "name": "宏旭-KY",
      "market": "TWSE",
      "foreign_daily": [
        -14,
        -30,
        -3,
        20,
        24,
        20
      ],
      "dealer_daily": [
        -1,
        0,
        -1,
        2,
        -1,
        5
      ]
    },
    {
      "code": "3224",
      "name": "三顧",
      "market": "TPEX",
      "foreign_daily": [
        0,
        -25,
        19,
        10,
        2,
        10
      ],
      "dealer_daily": [
        0,
        0,
        0,
        0,
        0,
        1
      ]
    },
    {
      "code": "5345",
      "name": "馥鴻",
      "market": "TPEX",
      "foreign_daily": [
        0,
        0,
        0,
        0,
        19,
        -3
      ],
      "dealer_daily": [
        0,
        0,
        0,
        0,
        0,
        1
      ]
    },
    {
      "code": "7642",
      "name": "昶瑞機電",
      "market": "TPEX",
      "foreign_daily": [
        -2,
        2,
        0,
        10,
        -1,
        7
      ],
      "dealer_daily": [
        0,
        1,
        0,
        0,
        0,
        0
      ]
    },
    {
      "code": "3713",
      "name": "新晶投控",
      "market": "TPEX",
      "foreign_daily": [
        13,
        0,
        -6,
        -3,
        -1,
        12
      ],
      "dealer_daily": [
        9,
        0,
        0,
        -3,
        -1,
        0
      ]
    },
    {
      "code": "7842",
      "name": "天能綠電",
      "market": "TPEX",
      "foreign_daily": [
        5,
        0,
        -2,
        1,
        4,
        7
      ],
      "dealer_daily": [
        0,
        0,
        2,
        0,
        0,
        0
      ]
    },
    {
      "code": "1530",
      "name": "亞崴",
      "market": "TWSE",
      "foreign_daily": [
        21,
        21,
        -40,
        -10,
        13,
        9
      ],
      "dealer_daily": [
        3,
        -1,
        0,
        -1,
        2,
        3
      ]
    },
    {
      "code": "9944",
      "name": "新麗",
      "market": "TWSE",
      "foreign_daily": [
        -4,
        8,
        -9,
        5,
        0,
        14
      ],
      "dealer_daily": [
        0,
        3,
        -1,
        0,
        0,
        1
      ]
    },
    {
      "code": "4432",
      "name": "銘旺實",
      "market": "TPEX",
      "foreign_daily": [
        -2,
        2,
        25,
        -9,
        3,
        -5
      ],
      "dealer_daily": [
        0,
        0,
        0,
        0,
        0,
        1
      ]
    },
    {
      "code": "2438",
      "name": "翔耀",
      "market": "TWSE",
      "foreign_daily": [
        24,
        31,
        -51,
        -32,
        11,
        29
      ],
      "dealer_daily": [
        2,
        1,
        -1,
        0,
        3,
        2
      ]
    },
    {
      "code": "2945",
      "name": "三商家購",
      "market": "TWSE",
      "foreign_daily": [
        10,
        -1,
        -1,
        3,
        -1,
        2
      ],
      "dealer_daily": [
        0,
        0,
        -2,
        0,
        0,
        10
      ]
    },
    {
      "code": "5013",
      "name": "強新",
      "market": "TPEX",
      "foreign_daily": [
        3,
        3,
        1,
        0,
        5,
        0
      ],
      "dealer_daily": [
        0,
        0,
        0,
        1,
        0,
        0
      ]
    },
    {
      "code": "5274",
      "name": "信驊",
      "market": "TPEX",
      "foreign_daily": [
        -24,
        -1,
        -87,
        76,
        22,
        26
      ],
      "dealer_daily": [
        0,
        0,
        5,
        1,
        4,
        -1
      ]
    },
    {
      "code": "4148",
      "name": "全宇生技-KY",
      "market": "TWSE",
      "foreign_daily": [
        20,
        -7,
        -2,
        -4,
        0,
        2
      ],
      "dealer_daily": [
        0,
        -1,
        3,
        -1,
        0,
        2
      ]
    },
    {
      "code": "1454",
      "name": "台富",
      "market": "TWSE",
      "foreign_daily": [
        7,
        -1,
        -9,
        5,
        3,
        4
      ],
      "dealer_daily": [
        2,
        1,
        2,
        0,
        0,
        -2
      ]
    },
    {
      "code": "6470",
      "name": "宇智",
      "market": "TPEX",
      "foreign_daily": [
        11,
        30,
        -31,
        -9,
        -5,
        12
      ],
      "dealer_daily": [
        0,
        0,
        0,
        1,
        0,
        0
      ]
    },
    {
      "code": "2511",
      "name": "太子",
      "market": "TWSE",
      "foreign_daily": [
        511,
        47,
        -756,
        100,
        -164,
        269
      ],
      "dealer_daily": [
        25,
        29,
        -10,
        8,
        -7,
        -11
      ]
    },
    {
      "code": "5310",
      "name": "天剛",
      "market": "TPEX",
      "foreign_daily": [
        1,
        1,
        0,
        0,
        2,
        3
      ],
      "dealer_daily": [
        1,
        0,
        0,
        0,
        0,
        1
      ]
    },
    {
      "code": "4706",
      "name": "大恭",
      "market": "TPEX",
      "foreign_daily": [
        0,
        2,
        2,
        0,
        4,
        -1
      ],
      "dealer_daily": [
        0,
        0,
        1,
        0,
        0,
        0
      ]
    },
    {
      "code": "9912",
      "name": "偉聯",
      "market": "TWSE",
      "foreign_daily": [
        9,
        -1,
        -2,
        -1,
        0,
        1
      ],
      "dealer_daily": [
        -1,
        0,
        0,
        0,
        0,
        3
      ]
    },
    {
      "code": "1410",
      "name": "南染",
      "market": "TWSE",
      "foreign_daily": [
        -1,
        8,
        -12,
        14,
        -3,
        0
      ],
      "dealer_daily": [
        2,
        0,
        -1,
        0,
        0,
        0
      ]
    },
    {
      "code": "3288",
      "name": "點晶",
      "market": "TPEX",
      "foreign_daily": [
        2,
        -10,
        11,
        -3,
        2,
        4
      ],
      "dealer_daily": [
        0,
        0,
        3,
        -1,
        0,
        0
      ]
    },
    {
      "code": "3672",
      "name": "康聯訊",
      "market": "TPEX",
      "foreign_daily": [
        0,
        0,
        0,
        0,
        2,
        4
      ],
      "dealer_daily": [
        0,
        2,
        0,
        0,
        0,
        1
      ]
    },
    {
      "code": "1475",
      "name": "業旺",
      "market": "TWSE",
      "foreign_daily": [
        1,
        0,
        -4,
        3,
        4,
        1
      ],
      "dealer_daily": [
        0,
        1,
        -1,
        0,
        0,
        1
      ]
    },
    {
      "code": "8367",
      "name": "建新國際",
      "market": "TWSE",
      "foreign_daily": [
        -5,
        1,
        -8,
        -3,
        11,
        9
      ],
      "dealer_daily": [
        0,
        1,
        2,
        0,
        -2,
        1
      ]
    },
    {
      "code": "5603",
      "name": "陸海",
      "market": "TPEX",
      "foreign_daily": [
        8,
        18,
        -19,
        7,
        -28,
        19
      ],
      "dealer_daily": [
        0,
        0,
        1,
        0,
        0,
        0
      ]
    },
    {
      "code": "8924",
      "name": "大田",
      "market": "TPEX",
      "foreign_daily": [
        3,
        36,
        -42,
        -7,
        5,
        10
      ],
      "dealer_daily": [
        1,
        0,
        0,
        1,
        0,
        0
      ]
    },
    {
      "code": "4972",
      "name": "湯石照明",
      "market": "TPEX",
      "foreign_daily": [
        3,
        3,
        0,
        0,
        -1,
        -1
      ],
      "dealer_daily": [
        0,
        1,
        0,
        0,
        0,
        0
      ]
    },
    {
      "code": "5355",
      "name": "佳總",
      "market": "TPEX",
      "foreign_daily": [
        -8,
        0,
        0,
        5,
        2,
        5
      ],
      "dealer_daily": [
        0,
        1,
        0,
        0,
        0,
        0
      ]
    },
    {
      "code": "6870",
      "name": "騰雲",
      "market": "TPEX",
      "foreign_daily": [
        -2,
        0,
        24,
        13,
        -6,
        -25
      ],
      "dealer_daily": [
        1,
        1,
        -1,
        0,
        -2,
        4
      ]
    },
    {
      "code": "7736",
      "name": "虎山",
      "market": "TWSE",
      "foreign_daily": [
        3,
        3,
        -2,
        0,
        -2,
        1
      ],
      "dealer_daily": [
        0,
        1,
        0,
        0,
        0,
        0
      ]
    },
    {
      "code": "1521",
      "name": "大億",
      "market": "TWSE",
      "foreign_daily": [
        -7,
        9,
        -9,
        9,
        -6,
        7
      ],
      "dealer_daily": [
        5,
        0,
        0,
        -2,
        3,
        0
      ]
    },
    {
      "code": "3171",
      "name": "炎洲流通",
      "market": "TPEX",
      "foreign_daily": [
        2,
        -3,
        -3,
        8,
        0,
        -1
      ],
      "dealer_daily": [
        0,
        0,
        0,
        0,
        0,
        9
      ]
    },
    {
      "code": "4114",
      "name": "健喬",
      "market": "TPEX",
      "foreign_daily": [
        595,
        -88,
        -638,
        735,
        -401,
        -200
      ],
      "dealer_daily": [
        0,
        0,
        0,
        0,
        1,
        0
      ]
    },
    {
      "code": "1103",
      "name": "嘉泥",
      "market": "TWSE",
      "foreign_daily": [
        33,
        81,
        -84,
        149,
        -150,
        -27
      ],
      "dealer_daily": [
        -1,
        10,
        22,
        2,
        -2,
        -13
      ]
    },
    {
      "code": "1418",
      "name": "東華",
      "market": "TWSE",
      "foreign_daily": [
        3,
        -1,
        -4,
        0,
        2,
        2
      ],
      "dealer_daily": [
        0,
        0,
        2,
        0,
        0,
        0
      ]
    },
    {
      "code": "9929",
      "name": "秋雨",
      "market": "TWSE",
      "foreign_daily": [
        3,
        -2,
        -4,
        3,
        2,
        0
      ],
      "dealer_daily": [
        -1,
        1,
        4,
        -1,
        0,
        1
      ]
    },
    {
      "code": "6240",
      "name": "松崗",
      "market": "TPEX",
      "foreign_daily": [
        3,
        0,
        -1,
        0,
        0,
        0
      ],
      "dealer_daily": [
        0,
        0,
        0,
        0,
        0,
        1
      ]
    },
    {
      "code": "6593",
      "name": "台灣銘板",
      "market": "TPEX",
      "foreign_daily": [
        0,
        20,
        -12,
        -9,
        24,
        -21
      ],
      "dealer_daily": [
        0,
        0,
        0,
        0,
        0,
        7
      ]
    },
    {
      "code": "6464",
      "name": "台數科",
      "market": "TWSE",
      "foreign_daily": [
        0,
        2,
        -3,
        5,
        2,
        -5
      ],
      "dealer_daily": [
        0,
        0,
        1,
        0,
        0,
        1
      ]
    },
    {
      "code": "1539",
      "name": "巨庭",
      "market": "TWSE",
      "foreign_daily": [
        -10,
        -9,
        -12,
        17,
        12,
        3
      ],
      "dealer_daily": [
        7,
        2,
        -3,
        1,
        0,
        -2
      ]
    },
    {
      "code": "6722",
      "name": "輝創",
      "market": "TWSE",
      "foreign_daily": [
        -10,
        -8,
        -14,
        0,
        29,
        4
      ],
      "dealer_daily": [
        1,
        0,
        8,
        -2,
        0,
        1
      ]
    },
    {
      "code": "8421",
      "name": "旭源",
      "market": "TPEX",
      "foreign_daily": [
        -5,
        -4,
        4,
        6,
        3,
        -3
      ],
      "dealer_daily": [
        0,
        0,
        0,
        2,
        0,
        0
      ]
    },
    {
      "code": "8917",
      "name": "欣泰",
      "market": "TPEX",
      "foreign_daily": [
        -1,
        1,
        -3,
        4,
        1,
        -1
      ],
      "dealer_daily": [
        0,
        0,
        0,
        0,
        0,
        1
      ]
    }
  ]
}