{
  "updated_at": "2026-06-27T20:33:26+08:00",
  "trading_days": [
    "2026-06-18",
    "2026-06-22",
    "2026-06-23",
    "2026-06-24",
    "2026-06-25",
    "2026-06-26"
  ],
  "note": "數值單位為「張」(股數÷1000);外資含陸資、自營商含自行+避險。資料僅供參考,非投資建議。",
  "stocks": [
    {
      "code": "2002",
      "name": "中鋼",
      "market": "TWSE",
      "foreign_daily": [
        319914,
        44582,
        -20144,
        14042,
        -9130,
        2636
      ],
      "dealer_daily": [
        811,
        1011,
        -138,
        42,
        -236,
        -316
      ]
    },
    {
      "code": "1301",
      "name": "台塑",
      "market": "TWSE",
      "foreign_daily": [
        142290,
        16495,
        -5532,
        20646,
        39475,
        -23336
      ],
      "dealer_daily": [
        375,
        938,
        -849,
        1164,
        -8,
        -1596
      ]
    },
    {
      "code": "2610",
      "name": "華航",
      "market": "TWSE",
      "foreign_daily": [
        19462,
        -4398,
        33755,
        61357,
        52216,
        3664
      ],
      "dealer_daily": [
        -44,
        2784,
        3814,
        7519,
        3236,
        -1801
      ]
    },
    {
      "code": "2303",
      "name": "聯電",
      "market": "TWSE",
      "foreign_daily": [
        65777,
        -11971,
        27580,
        7333,
        11768,
        -16701
      ],
      "dealer_daily": [
        8305,
        -216,
        3562,
        9436,
        3926,
        -2532
      ]
    },
    {
      "code": "2449",
      "name": "京元電子",
      "market": "TWSE",
      "foreign_daily": [
        17379,
        20077,
        31582,
        3806,
        7790,
        2555
      ],
      "dealer_daily": [
        1845,
        493,
        -429,
        -108,
        258,
        -418
      ]
    },
    {
      "code": "2618",
      "name": "長榮航",
      "market": "TWSE",
      "foreign_daily": [
        10507,
        -3078,
        6699,
        25401,
        13423,
        7123
      ],
      "dealer_daily": [
        451,
        546,
        1512,
        1719,
        524,
        -369
      ]
    },
    {
      "code": "3711",
      "name": "日月光投控",
      "market": "TWSE",
      "foreign_daily": [
        13364,
        15663,
        10811,
        2322,
        235,
        6483
      ],
      "dealer_daily": [
        1058,
        440,
        -339,
        -71,
        -546,
        13
      ]
    },
    {
      "code": "2887",
      "name": "台新新光金",
      "market": "TWSE",
      "foreign_daily": [
        3370,
        13106,
        20639,
        -11518,
        10397,
        7636
      ],
      "dealer_daily": [
        131,
        408,
        1007,
        2764,
        -729,
        2853
      ]
    },
    {
      "code": "5880",
      "name": "合庫金",
      "market": "TWSE",
      "foreign_daily": [
        11374,
        -5833,
        11119,
        2563,
        23418,
        837
      ],
      "dealer_daily": [
        98,
        48,
        305,
        465,
        108,
        555
      ]
    },
    {
      "code": "6213",
      "name": "聯茂",
      "market": "TWSE",
      "foreign_daily": [
        4331,
        13114,
        -86,
        3765,
        3957,
        3833
      ],
      "dealer_daily": [
        483,
        444,
        -419,
        194,
        174,
        91
      ]
    },
    {
      "code": "8150",
      "name": "南茂",
      "market": "TWSE",
      "foreign_daily": [
        15844,
        8686,
        11950,
        -6239,
        -21119,
        18341
      ],
      "dealer_daily": [
        1098,
        876,
        838,
        -670,
        -1551,
        68
      ]
    },
    {
      "code": "2369",
      "name": "菱生",
      "market": "TWSE",
      "foreign_daily": [
        4283,
        8750,
        5916,
        4288,
        -2172,
        -2229
      ],
      "dealer_daily": [
        550,
        460,
        626,
        -516,
        -177,
        -84
      ]
    },
    {
      "code": "2891",
      "name": "中信金",
      "market": "TWSE",
      "foreign_daily": [
        19245,
        -5117,
        11036,
        -9359,
        2816,
        -918
      ],
      "dealer_daily": [
        510,
        -279,
        798,
        305,
        -469,
        2557
      ]
    },
    {
      "code": "3374",
      "name": "精材",
      "market": "TPEX",
      "foreign_daily": [
        984,
        1838,
        11418,
        3511,
        269,
        -648
      ],
      "dealer_daily": [
        353,
        888,
        1070,
        1904,
        301,
        -323
      ]
    },
    {
      "code": "6919",
      "name": "康霈*",
      "market": "TWSE",
      "foreign_daily": [
        25486,
        2498,
        -5599,
        -1787,
        -2263,
        -1298
      ],
      "dealer_daily": [
        191,
        185,
        -109,
        20,
        -9,
        -24
      ]
    },
    {
      "code": "2441",
      "name": "超豐",
      "market": "TWSE",
      "foreign_daily": [
        4270,
        8439,
        1097,
        4023,
        -2532,
        -877
      ],
      "dealer_daily": [
        440,
        216,
        -232,
        244,
        -291,
        -228
      ]
    },
    {
      "code": "2812",
      "name": "台中銀",
      "market": "TWSE",
      "foreign_daily": [
        -1513,
        -5005,
        11991,
        870,
        7521,
        446
      ],
      "dealer_daily": [
        -75,
        38,
        33,
        111,
        121,
        118
      ]
    },
    {
      "code": "8046",
      "name": "南電",
      "market": "TWSE",
      "foreign_daily": [
        -5808,
        -2620,
        11482,
        3229,
        4303,
        3130
      ],
      "dealer_daily": [
        121,
        401,
        439,
        368,
        297,
        -843
      ]
    },
    {
      "code": "6770",
      "name": "力積電",
      "market": "TWSE",
      "foreign_daily": [
        14672,
        27410,
        -14053,
        83296,
        -87947,
        -10379
      ],
      "dealer_daily": [
        2189,
        1303,
        238,
        3901,
        -1758,
        -2769
      ]
    },
    {
      "code": "2606",
      "name": "裕民",
      "market": "TWSE",
      "foreign_daily": [
        6887,
        4676,
        297,
        1120,
        1500,
        -2631
      ],
      "dealer_daily": [
        129,
        -19,
        -29,
        8,
        -12,
        36
      ]
    },
    {
      "code": "3264",
      "name": "欣銓",
      "market": "TPEX",
      "foreign_daily": [
        4300,
        3451,
        3402,
        228,
        226,
        -193
      ],
      "dealer_daily": [
        340,
        219,
        -148,
        -53,
        -50,
        -109
      ]
    },
    {
      "code": "1477",
      "name": "聚陽",
      "market": "TWSE",
      "foreign_daily": [
        2832,
        369,
        2164,
        3796,
        2757,
        -693
      ],
      "dealer_daily": [
        -25,
        -41,
        -7,
        85,
        100,
        63
      ]
    },
    {
      "code": "6257",
      "name": "矽格",
      "market": "TWSE",
      "foreign_daily": [
        3013,
        7695,
        3301,
        -259,
        92,
        -3465
      ],
      "dealer_daily": [
        879,
        561,
        -251,
        -58,
        -167,
        -402
      ]
    },
    {
      "code": "2401",
      "name": "凌陽",
      "market": "TWSE",
      "foreign_daily": [
        7428,
        -1627,
        2537,
        3140,
        86,
        -1995
      ],
      "dealer_daily": [
        462,
        275,
        -251,
        270,
        -154,
        -417
      ]
    },
    {
      "code": "3715",
      "name": "定穎投控",
      "market": "TWSE",
      "foreign_daily": [
        2139,
        15310,
        -875,
        -2615,
        -2339,
        -2609
      ],
      "dealer_daily": [
        98,
        538,
        -461,
        -8,
        -120,
        -33
      ]
    },
    {
      "code": "2207",
      "name": "和泰車",
      "market": "TWSE",
      "foreign_daily": [
        7673,
        -68,
        286,
        -168,
        27,
        199
      ],
      "dealer_daily": [
        18,
        4,
        2,
        -1,
        -2,
        -2
      ]
    },
    {
      "code": "2347",
      "name": "聯強",
      "market": "TWSE",
      "foreign_daily": [
        2552,
        1101,
        776,
        2489,
        2178,
        -1334
      ],
      "dealer_daily": [
        34,
        107,
        36,
        154,
        7,
        142
      ]
    },
    {
      "code": "1714",
      "name": "和桐",
      "market": "TWSE",
      "foreign_daily": [
        -5236,
        48,
        4858,
        3384,
        2691,
        1711
      ],
      "dealer_daily": [
        -72,
        195,
        565,
        259,
        -60,
        338
      ]
    },
    {
      "code": "1326",
      "name": "台化",
      "market": "TWSE",
      "foreign_daily": [
        429,
        10089,
        -11592,
        20605,
        5900,
        -18103
      ],
      "dealer_daily": [
        437,
        862,
        -850,
        867,
        477,
        -1148
      ]
    },
    {
      "code": "8054",
      "name": "安國",
      "market": "TPEX",
      "foreign_daily": [
        664,
        2273,
        4273,
        1950,
        -1727,
        -271
      ],
      "dealer_daily": [
        9,
        161,
        85,
        211,
        -50,
        -89
      ]
    },
    {
      "code": "3045",
      "name": "台灣大",
      "market": "TWSE",
      "foreign_daily": [
        1403,
        -1089,
        2643,
        3062,
        3774,
        -3035
      ],
      "dealer_daily": [
        -92,
        634,
        -305,
        -135,
        -131,
        377
      ]
    },
    {
      "code": "2867",
      "name": "三商壽",
      "market": "TWSE",
      "foreign_daily": [
        4868,
        3249,
        4472,
        -5127,
        -349,
        -754
      ],
      "dealer_daily": [
        1034,
        893,
        1151,
        653,
        3084,
        241
      ]
    },
    {
      "code": "3033",
      "name": "威健",
      "market": "TWSE",
      "foreign_daily": [
        1784,
        4495,
        -3032,
        -453,
        -763,
        4143
      ],
      "dealer_daily": [
        20,
        304,
        13,
        119,
        39,
        -15
      ]
    },
    {
      "code": "4938",
      "name": "和碩",
      "market": "TWSE",
      "foreign_daily": [
        3036,
        -3524,
        -1377,
        7649,
        5618,
        -5282
      ],
      "dealer_daily": [
        175,
        17,
        -399,
        314,
        279,
        -124
      ]
    },
    {
      "code": "6226",
      "name": "光鼎",
      "market": "TWSE",
      "foreign_daily": [
        -96,
        611,
        799,
        605,
        -25,
        4130
      ],
      "dealer_daily": [
        -2,
        -2,
        -1,
        3,
        89,
        -70
      ]
    },
    {
      "code": "6672",
      "name": "騰輝電子-KY",
      "market": "TWSE",
      "foreign_daily": [
        1959,
        43,
        375,
        279,
        2843,
        491
      ],
      "dealer_daily": [
        79,
        -47,
        -20,
        69,
        110,
        -89
      ]
    },
    {
      "code": "6962",
      "name": "奕力-KY",
      "market": "TWSE",
      "foreign_daily": [
        1758,
        3838,
        120,
        1200,
        -435,
        -524
      ],
      "dealer_daily": [
        38,
        92,
        -25,
        10,
        -16,
        -89
      ]
    },
    {
      "code": "1102",
      "name": "亞泥",
      "market": "TWSE",
      "foreign_daily": [
        1858,
        15,
        -2476,
        980,
        1336,
        3929
      ],
      "dealer_daily": [
        349,
        1077,
        186,
        96,
        1061,
        178
      ]
    },
    {
      "code": "6695",
      "name": "芯鼎",
      "market": "TWSE",
      "foreign_daily": [
        560,
        206,
        1949,
        2977,
        -691,
        588
      ],
      "dealer_daily": [
        0,
        30,
        -27,
        30,
        -30,
        -2
      ]
    },
    {
      "code": "1312",
      "name": "國喬",
      "market": "TWSE",
      "foreign_daily": [
        -125,
        1264,
        1022,
        2688,
        2675,
        -2066
      ],
      "dealer_daily": [
        136,
        151,
        -159,
        58,
        64,
        -140
      ]
    },
    {
      "code": "3016",
      "name": "嘉晶",
      "market": "TWSE",
      "foreign_daily": [
        271,
        1390,
        1017,
        2653,
        -305,
        73
      ],
      "dealer_daily": [
        57,
        156,
        27,
        -191,
        -1,
        -40
      ]
    },
    {
      "code": "2646",
      "name": "星宇航空",
      "market": "TWSE",
      "foreign_daily": [
        758,
        -1596,
        3997,
        1802,
        376,
        -533
      ],
      "dealer_daily": [
        145,
        4,
        1,
        33,
        -4,
        -100
      ]
    },
    {
      "code": "2436",
      "name": "偉詮電",
      "market": "TWSE",
      "foreign_daily": [
        1621,
        4171,
        -789,
        168,
        294,
        -1144
      ],
      "dealer_daily": [
        117,
        537,
        -131,
        -51,
        -88,
        -153
      ]
    },
    {
      "code": "2105",
      "name": "正新",
      "market": "TWSE",
      "foreign_daily": [
        1383,
        2686,
        -8115,
        -276,
        6219,
        2333
      ],
      "dealer_daily": [
        598,
        1378,
        223,
        -49,
        77,
        78
      ]
    },
    {
      "code": "5469",
      "name": "瀚宇博",
      "market": "TWSE",
      "foreign_daily": [
        451,
        1349,
        -1943,
        -739,
        517,
        4372
      ],
      "dealer_daily": [
        1,
        115,
        -39,
        -37,
        -4,
        57
      ]
    },
    {
      "code": "1229",
      "name": "聯華",
      "market": "TWSE",
      "foreign_daily": [
        3,
        -809,
        1222,
        2206,
        2171,
        -841
      ],
      "dealer_daily": [
        54,
        -5,
        4,
        -1,
        -6,
        57
      ]
    },
    {
      "code": "6191",
      "name": "精成科",
      "market": "TWSE",
      "foreign_daily": [
        328,
        825,
        -3016,
        -855,
        -347,
        6981
      ],
      "dealer_daily": [
        7,
        73,
        -83,
        -43,
        -28,
        153
      ]
    },
    {
      "code": "1907",
      "name": "永豐餘",
      "market": "TWSE",
      "foreign_daily": [
        1902,
        -25,
        370,
        987,
        270,
        291
      ],
      "dealer_daily": [
        19,
        10,
        4,
        -7,
        0,
        -8
      ]
    },
    {
      "code": "4306",
      "name": "炎洲",
      "market": "TWSE",
      "foreign_daily": [
        853,
        1179,
        50,
        253,
        768,
        590
      ],
      "dealer_daily": [
        105,
        2,
        0,
        7,
        1,
        -8
      ]
    },
    {
      "code": "3028",
      "name": "增你強",
      "market": "TWSE",
      "foreign_daily": [
        -190,
        3093,
        -1405,
        -64,
        -711,
        2914
      ],
      "dealer_daily": [
        10,
        69,
        24,
        12,
        -25,
        76
      ]
    },
    {
      "code": "2363",
      "name": "矽統",
      "market": "TWSE",
      "foreign_daily": [
        2541,
        2455,
        1057,
        1625,
        1839,
        -6119
      ],
      "dealer_daily": [
        38,
        384,
        -20,
        555,
        547,
        -974
      ]
    },
    {
      "code": "2634",
      "name": "漢翔",
      "market": "TWSE",
      "foreign_daily": [
        221,
        4318,
        -332,
        -262,
        -1654,
        1036
      ],
      "dealer_daily": [
        19,
        1153,
        -979,
        -11,
        -32,
        88
      ]
    },
    {
      "code": "2103",
      "name": "台橡",
      "market": "TWSE",
      "foreign_daily": [
        1963,
        -29,
        -364,
        2561,
        144,
        -1008
      ],
      "dealer_daily": [
        32,
        -59,
        63,
        191,
        -87,
        -24
      ]
    },
    {
      "code": "2458",
      "name": "義隆",
      "market": "TWSE",
      "foreign_daily": [
        2021,
        -1832,
        -302,
        -54,
        3265,
        116
      ],
      "dealer_daily": [
        298,
        -48,
        -71,
        -31,
        84,
        -135
      ]
    },
    {
      "code": "4551",
      "name": "智伸科",
      "market": "TWSE",
      "foreign_daily": [
        1098,
        1514,
        404,
        -7,
        217,
        -171
      ],
      "dealer_daily": [
        25,
        15,
        -12,
        -9,
        -8,
        -8
      ]
    },
    {
      "code": "9933",
      "name": "中鼎",
      "market": "TWSE",
      "foreign_daily": [
        -403,
        2685,
        -187,
        -13,
        1338,
        -486
      ],
      "dealer_daily": [
        12,
        -108,
        82,
        37,
        -53,
        106
      ]
    },
    {
      "code": "2472",
      "name": "立隆電",
      "market": "TWSE",
      "foreign_daily": [
        310,
        -1128,
        137,
        -471,
        2936,
        1144
      ],
      "dealer_daily": [
        264,
        -238,
        -20,
        36,
        107,
        -121
      ]
    },
    {
      "code": "8016",
      "name": "矽創",
      "market": "TWSE",
      "foreign_daily": [
        -13,
        1063,
        -15,
        301,
        958,
        532
      ],
      "dealer_daily": [
        9,
        91,
        9,
        4,
        48,
        -35
      ]
    },
    {
      "code": "3006",
      "name": "晶豪科",
      "market": "TWSE",
      "foreign_daily": [
        2809,
        1583,
        2771,
        -1601,
        -3045,
        253
      ],
      "dealer_daily": [
        624,
        519,
        -18,
        -104,
        -194,
        -147
      ]
    },
    {
      "code": "2030",
      "name": "彰源",
      "market": "TWSE",
      "foreign_daily": [
        501,
        2239,
        836,
        -789,
        -90,
        50
      ],
      "dealer_daily": [
        14,
        -1,
        2,
        6,
        -28,
        18
      ]
    },
    {
      "code": "3010",
      "name": "華立",
      "market": "TWSE",
      "foreign_daily": [
        638,
        245,
        361,
        528,
        666,
        295
      ],
      "dealer_daily": [
        12,
        -1,
        7,
        4,
        -11,
        -9
      ]
    },
    {
      "code": "8021",
      "name": "尖點",
      "market": "TWSE",
      "foreign_daily": [
        234,
        1459,
        483,
        72,
        8,
        403
      ],
      "dealer_daily": [
        19,
        122,
        72,
        55,
        -14,
        -19
      ]
    },
    {
      "code": "3034",
      "name": "聯詠",
      "market": "TWSE",
      "foreign_daily": [
        1399,
        4474,
        170,
        -657,
        305,
        -3045
      ],
      "dealer_daily": [
        208,
        266,
        -139,
        199,
        196,
        -112
      ]
    },
    {
      "code": "2481",
      "name": "強茂",
      "market": "TWSE",
      "foreign_daily": [
        -386,
        -94,
        13980,
        -3038,
        -8160,
        314
      ],
      "dealer_daily": [
        348,
        316,
        201,
        -314,
        -211,
        -114
      ]
    },
    {
      "code": "1904",
      "name": "正隆",
      "market": "TWSE",
      "foreign_daily": [
        725,
        83,
        708,
        535,
        -119,
        583
      ],
      "dealer_daily": [
        -8,
        13,
        7,
        7,
        0,
        -11
      ]
    },
    {
      "code": "1305",
      "name": "華夏",
      "market": "TWSE",
      "foreign_daily": [
        -342,
        996,
        -1128,
        1861,
        224,
        873
      ],
      "dealer_daily": [
        59,
        79,
        -45,
        44,
        52,
        -38
      ]
    },
    {
      "code": "2897",
      "name": "王道銀行",
      "market": "TWSE",
      "foreign_daily": [
        1695,
        550,
        3344,
        -2234,
        591,
        -1522
      ],
      "dealer_daily": [
        0,
        35,
        6,
        -5,
        21,
        16
      ]
    },
    {
      "code": "1444",
      "name": "力麗",
      "market": "TWSE",
      "foreign_daily": [
        173,
        233,
        416,
        136,
        193,
        1230
      ],
      "dealer_daily": [
        81,
        -2,
        2,
        0,
        0,
        -5
      ]
    },
    {
      "code": "2836",
      "name": "高雄銀",
      "market": "TWSE",
      "foreign_daily": [
        167,
        -243,
        892,
        366,
        862,
        309
      ],
      "dealer_daily": [
        -5,
        1,
        4,
        -3,
        24,
        -12
      ]
    },
    {
      "code": "2360",
      "name": "致茂",
      "market": "TWSE",
      "foreign_daily": [
        467,
        825,
        73,
        516,
        260,
        186
      ],
      "dealer_daily": [
        -1,
        21,
        14,
        31,
        4,
        -6
      ]
    },
    {
      "code": "3624",
      "name": "光頡",
      "market": "TPEX",
      "foreign_daily": [
        -121,
        2574,
        -1935,
        762,
        729,
        203
      ],
      "dealer_daily": [
        70,
        36,
        -100,
        19,
        32,
        25
      ]
    },
    {
      "code": "1210",
      "name": "大成",
      "market": "TWSE",
      "foreign_daily": [
        396,
        -202,
        245,
        555,
        1589,
        -378
      ],
      "dealer_daily": [
        108,
        5,
        5,
        17,
        153,
        5
      ]
    },
    {
      "code": "2368",
      "name": "金像電",
      "market": "TWSE",
      "foreign_daily": [
        -832,
        616,
        -2313,
        1083,
        1598,
        1993
      ],
      "dealer_daily": [
        -35,
        107,
        99,
        99,
        -35,
        -135
      ]
    },
    {
      "code": "6202",
      "name": "盛群",
      "market": "TWSE",
      "foreign_daily": [
        567,
        1652,
        -2284,
        -683,
        -264,
        3150
      ],
      "dealer_daily": [
        167,
        174,
        24,
        -17,
        49,
        -41
      ]
    },
    {
      "code": "1308",
      "name": "亞聚",
      "market": "TWSE",
      "foreign_daily": [
        446,
        49,
        -891,
        1622,
        845,
        55
      ],
      "dealer_daily": [
        -4,
        31,
        -43,
        41,
        -3,
        -13
      ]
    },
    {
      "code": "1310",
      "name": "台苯",
      "market": "TWSE",
      "foreign_daily": [
        -772,
        4720,
        -591,
        -682,
        -526,
        -39
      ],
      "dealer_daily": [
        -51,
        30,
        -29,
        11,
        18,
        45
      ]
    },
    {
      "code": "2484",
      "name": "希華",
      "market": "TWSE",
      "foreign_daily": [
        -220,
        -1553,
        1558,
        -268,
        -850,
        3342
      ],
      "dealer_daily": [
        -67,
        -143,
        29,
        47,
        -22,
        289
      ]
    },
    {
      "code": "2527",
      "name": "宏璟",
      "market": "TWSE",
      "foreign_daily": [
        165,
        -195,
        670,
        21,
        403,
        941
      ],
      "dealer_daily": [
        17,
        0,
        -2,
        4,
        0,
        -2
      ]
    },
    {
      "code": "6179",
      "name": "亞通",
      "market": "TPEX",
      "foreign_daily": [
        1003,
        488,
        705,
        -517,
        136,
        189
      ],
      "dealer_daily": [
        183,
        -186,
        190,
        20,
        -274,
        135
      ]
    },
    {
      "code": "6278",
      "name": "台表科",
      "market": "TWSE",
      "foreign_daily": [
        -489,
        866,
        1366,
        648,
        -1066,
        661
      ],
      "dealer_daily": [
        185,
        -1,
        41,
        -35,
        106,
        -80
      ]
    },
    {
      "code": "3591",
      "name": "艾笛森",
      "market": "TWSE",
      "foreign_daily": [
        468,
        1153,
        1639,
        -2292,
        921,
        92
      ],
      "dealer_daily": [
        -2,
        101,
        -103,
        81,
        -70,
        -6
      ]
    },
    {
      "code": "4764",
      "name": "雙鍵",
      "market": "TWSE",
      "foreign_daily": [
        997,
        -406,
        981,
        -102,
        223,
        149
      ],
      "dealer_daily": [
        30,
        -9,
        14,
        -39,
        7,
        6
      ]
    },
    {
      "code": "6719",
      "name": "力智",
      "market": "TWSE",
      "foreign_daily": [
        1260,
        1731,
        321,
        -1000,
        -817,
        262
      ],
      "dealer_daily": [
        63,
        112,
        -2,
        165,
        32,
        -114
      ]
    },
    {
      "code": "2820",
      "name": "華票",
      "market": "TWSE",
      "foreign_daily": [
        930,
        -157,
        713,
        730,
        1346,
        -1922
      ],
      "dealer_daily": [
        6,
        -17,
        9,
        -3,
        15,
        -7
      ]
    },
    {
      "code": "2547",
      "name": "日勝生",
      "market": "TWSE",
      "foreign_daily": [
        635,
        -1655,
        759,
        115,
        1168,
        603
      ],
      "dealer_daily": [
        28,
        -16,
        1,
        3,
        9,
        1
      ]
    },
    {
      "code": "2645",
      "name": "長榮航太",
      "market": "TWSE",
      "foreign_daily": [
        467,
        367,
        335,
        166,
        -31,
        247
      ],
      "dealer_daily": [
        -12,
        10,
        3,
        1,
        1,
        -1
      ]
    },
    {
      "code": "3221",
      "name": "台嘉碩",
      "market": "TPEX",
      "foreign_daily": [
        160,
        0,
        -424,
        -398,
        -12,
        2150
      ],
      "dealer_daily": [
        30,
        -2,
        -31,
        -1,
        -13,
        128
      ]
    },
    {
      "code": "6757",
      "name": "台灣虎航",
      "market": "TWSE",
      "foreign_daily": [
        -1628,
        73,
        1089,
        -688,
        2620,
        1
      ],
      "dealer_daily": [
        -35,
        30,
        72,
        392,
        89,
        -405
      ]
    },
    {
      "code": "4526",
      "name": "東台",
      "market": "TWSE",
      "foreign_daily": [
        -877,
        5689,
        -1891,
        182,
        -1652,
        -138
      ],
      "dealer_daily": [
        25,
        114,
        -59,
        14,
        11,
        -35
      ]
    },
    {
      "code": "3014",
      "name": "聯陽",
      "market": "TWSE",
      "foreign_daily": [
        792,
        396,
        208,
        -307,
        882,
        -660
      ],
      "dealer_daily": [
        -3,
        5,
        15,
        76,
        69,
        -58
      ]
    },
    {
      "code": "6129",
      "name": "普誠",
      "market": "TPEX",
      "foreign_daily": [
        -43,
        941,
        347,
        92,
        -611,
        581
      ],
      "dealer_daily": [
        0,
        0,
        1,
        25,
        -24,
        0
      ]
    },
    {
      "code": "1227",
      "name": "佳格",
      "market": "TWSE",
      "foreign_daily": [
        311,
        -74,
        274,
        129,
        816,
        -278
      ],
      "dealer_daily": [
        44,
        -5,
        2,
        -1,
        6,
        -7
      ]
    },
    {
      "code": "4952",
      "name": "凌通",
      "market": "TWSE",
      "foreign_daily": [
        523,
        476,
        48,
        154,
        -78,
        -13
      ],
      "dealer_daily": [
        1,
        -2,
        4,
        -1,
        -5,
        17
      ]
    },
    {
      "code": "3402",
      "name": "漢科",
      "market": "TPEX",
      "foreign_daily": [
        17,
        201,
        -100,
        53,
        1111,
        -189
      ],
      "dealer_daily": [
        -2,
        0,
        -5,
        -1,
        31,
        -5
      ]
    },
    {
      "code": "3588",
      "name": "通嘉",
      "market": "TWSE",
      "foreign_daily": [
        144,
        646,
        420,
        -102,
        -178,
        128
      ],
      "dealer_daily": [
        -2,
        27,
        -22,
        37,
        -35,
        3
      ]
    },
    {
      "code": "3217",
      "name": "優群",
      "market": "TPEX",
      "foreign_daily": [
        -249,
        195,
        63,
        232,
        838,
        -34
      ],
      "dealer_daily": [
        0,
        7,
        -17,
        9,
        296,
        73
      ]
    },
    {
      "code": "8042",
      "name": "金山電",
      "market": "TPEX",
      "foreign_daily": [
        19,
        249,
        138,
        192,
        259,
        171
      ],
      "dealer_daily": [
        45,
        -22,
        44,
        32,
        71,
        -51
      ]
    },
    {
      "code": "5328",
      "name": "華容",
      "market": "TPEX",
      "foreign_daily": [
        3673,
        -6375,
        -148,
        -2637,
        2765,
        3738
      ],
      "dealer_daily": [
        273,
        -97,
        -198,
        140,
        125,
        249
      ]
    },
    {
      "code": "6173",
      "name": "信昌電",
      "market": "TPEX",
      "foreign_daily": [
        317,
        107,
        283,
        162,
        41,
        76
      ],
      "dealer_daily": [
        427,
        48,
        -78,
        161,
        -63,
        -310
      ]
    },
    {
      "code": "1709",
      "name": "和益",
      "market": "TWSE",
      "foreign_daily": [
        129,
        -318,
        19,
        242,
        332,
        578
      ],
      "dealer_daily": [
        13,
        1,
        -3,
        0,
        0,
        9
      ]
    },
    {
      "code": "4991",
      "name": "環宇-KY",
      "market": "TPEX",
      "foreign_daily": [
        195,
        181,
        450,
        189,
        93,
        -169
      ],
      "dealer_daily": [
        43,
        5,
        88,
        13,
        12,
        30
      ]
    },
    {
      "code": "4968",
      "name": "立積",
      "market": "TWSE",
      "foreign_daily": [
        257,
        306,
        322,
        216,
        -51,
        -112
      ],
      "dealer_daily": [
        12,
        12,
        12,
        0,
        10,
        -26
      ]
    },
    {
      "code": "7827",
      "name": "漢康-KY創",
      "market": "TWSE",
      "foreign_daily": [
        -5,
        -108,
        497,
        86,
        212,
        221
      ],
      "dealer_daily": [
        2,
        2,
        -2,
        2,
        -2,
        2
      ]
    },
    {
      "code": "3257",
      "name": "虹冠電",
      "market": "TWSE",
      "foreign_daily": [
        414,
        514,
        -397,
        416,
        99,
        -173
      ],
      "dealer_daily": [
        8,
        12,
        3,
        -20,
        0,
        1
      ]
    },
    {
      "code": "2850",
      "name": "新產",
      "market": "TWSE",
      "foreign_daily": [
        179,
        184,
        251,
        11,
        120,
        109
      ],
      "dealer_daily": [
        15,
        0,
        3,
        -1,
        1,
        -3
      ]
    },
    {
      "code": "4164",
      "name": "承業醫",
      "market": "TWSE",
      "foreign_daily": [
        311,
        -197,
        247,
        123,
        46,
        286
      ],
      "dealer_daily": [
        4,
        4,
        2,
        0,
        1,
        3
      ]
    },
    {
      "code": "5536",
      "name": "聖暉*",
      "market": "TPEX",
      "foreign_daily": [
        270,
        236,
        -51,
        -38,
        21,
        371
      ],
      "dealer_daily": [
        16,
        -11,
        -4,
        9,
        4,
        -11
      ]
    },
    {
      "code": "7712",
      "name": "博盛半導體",
      "market": "TPEX",
      "foreign_daily": [
        443,
        192,
        145,
        -193,
        79,
        135
      ],
      "dealer_daily": [
        112,
        -6,
        33,
        33,
        -5,
        -23
      ]
    },
    {
      "code": "5236",
      "name": "凌陽創新",
      "market": "TPEX",
      "foreign_daily": [
        153,
        208,
        223,
        102,
        15,
        72
      ],
      "dealer_daily": [
        3,
        8,
        -1,
        -3,
        0,
        -2
      ]
    },
    {
      "code": "3311",
      "name": "閎暉",
      "market": "TWSE",
      "foreign_daily": [
        83,
        737,
        -31,
        -130,
        28,
        78
      ],
      "dealer_daily": [
        -2,
        1,
        4,
        -1,
        0,
        0
      ]
    },
    {
      "code": "2460",
      "name": "建通",
      "market": "TWSE",
      "foreign_daily": [
        -19,
        590,
        216,
        1866,
        -2053,
        156
      ],
      "dealer_daily": [
        6,
        5,
        -1,
        1,
        -1,
        -2
      ]
    },
    {
      "code": "6488",
      "name": "環球晶",
      "market": "TPEX",
      "foreign_daily": [
        1012,
        628,
        -572,
        -474,
        171,
        -29
      ],
      "dealer_daily": [
        -481,
        178,
        478,
        228,
        33,
        -179
      ]
    },
    {
      "code": "2852",
      "name": "第一保",
      "market": "TWSE",
      "foreign_daily": [
        -3,
        117,
        518,
        -106,
        216,
        -8
      ],
      "dealer_daily": [
        7,
        -10,
        0,
        0,
        8,
        -1
      ]
    },
    {
      "code": "4532",
      "name": "瑞智",
      "market": "TWSE",
      "foreign_daily": [
        -510,
        592,
        -181,
        372,
        763,
        -311
      ],
      "dealer_daily": [
        62,
        -2,
        17,
        -3,
        0,
        -2
      ]
    },
    {
      "code": "6491",
      "name": "晶碩",
      "market": "TWSE",
      "foreign_daily": [
        349,
        -20,
        97,
        227,
        18,
        40
      ],
      "dealer_daily": [
        12,
        0,
        6,
        0,
        -3,
        1
      ]
    },
    {
      "code": "6691",
      "name": "洋基工程",
      "market": "TWSE",
      "foreign_daily": [
        80,
        111,
        37,
        121,
        376,
        -14
      ],
      "dealer_daily": [
        6,
        15,
        -11,
        27,
        15,
        -5
      ]
    },
    {
      "code": "5230",
      "name": "雷笛克光學",
      "market": "TPEX",
      "foreign_daily": [
        -16,
        14,
        -109,
        5,
        506,
        302
      ],
      "dealer_daily": [
        0,
        0,
        -4,
        0,
        4,
        8
      ]
    },
    {
      "code": "1309",
      "name": "台達化",
      "market": "TWSE",
      "foreign_daily": [
        -383,
        581,
        -396,
        682,
        -170,
        385
      ],
      "dealer_daily": [
        -45,
        73,
        -52,
        33,
        -4,
        18
      ]
    },
    {
      "code": "6715",
      "name": "嘉基",
      "market": "TWSE",
      "foreign_daily": [
        7,
        249,
        458,
        26,
        -15,
        -32
      ],
      "dealer_daily": [
        -16,
        11,
        70,
        -28,
        -25,
        2
      ]
    },
    {
      "code": "6275",
      "name": "元山",
      "market": "TPEX",
      "foreign_daily": [
        -63,
        551,
        439,
        -90,
        -82,
        -73
      ],
      "dealer_daily": [
        0,
        3,
        25,
        -2,
        -10,
        -12
      ]
    },
    {
      "code": "3356",
      "name": "奇偶",
      "market": "TWSE",
      "foreign_daily": [
        776,
        254,
        -1,
        171,
        -185,
        -341
      ],
      "dealer_daily": [
        3,
        3,
        4,
        0,
        -1,
        -1
      ]
    },
    {
      "code": "3504",
      "name": "揚明光",
      "market": "TWSE",
      "foreign_daily": [
        1158,
        -2,
        -36,
        -189,
        -560,
        296
      ],
      "dealer_daily": [
        1,
        2,
        1,
        0,
        0,
        -2
      ]
    },
    {
      "code": "9921",
      "name": "巨大",
      "market": "TWSE",
      "foreign_daily": [
        -711,
        421,
        -400,
        -56,
        456,
        957
      ],
      "dealer_daily": [
        8,
        0,
        -14,
        9,
        3,
        0
      ]
    },
    {
      "code": "1905",
      "name": "華紙",
      "market": "TWSE",
      "foreign_daily": [
        4722,
        -1118,
        -1255,
        -796,
        -704,
        -193
      ],
      "dealer_daily": [
        -319,
        601,
        -165,
        41,
        -42,
        -88
      ]
    },
    {
      "code": "2478",
      "name": "大毅",
      "market": "TWSE",
      "foreign_daily": [
        -3114,
        1127,
        555,
        1287,
        461,
        321
      ],
      "dealer_daily": [
        9,
        28,
        -22,
        21,
        3,
        30
      ]
    },
    {
      "code": "5471",
      "name": "松翰",
      "market": "TWSE",
      "foreign_daily": [
        -1165,
        994,
        -420,
        831,
        292,
        83
      ],
      "dealer_daily": [
        -1,
        5,
        20,
        0,
        2,
        3
      ]
    },
    {
      "code": "6271",
      "name": "同欣電",
      "market": "TWSE",
      "foreign_daily": [
        819,
        2047,
        -782,
        -1109,
        1756,
        -2119
      ],
      "dealer_daily": [
        227,
        273,
        -97,
        31,
        272,
        -117
      ]
    },
    {
      "code": "9940",
      "name": "信義",
      "market": "TWSE",
      "foreign_daily": [
        51,
        130,
        157,
        164,
        25,
        72
      ],
      "dealer_daily": [
        16,
        7,
        15,
        40,
        8,
        9
      ]
    },
    {
      "code": "6409",
      "name": "旭隼",
      "market": "TWSE",
      "foreign_daily": [
        -36,
        95,
        -107,
        -11,
        818,
        -162
      ],
      "dealer_daily": [
        -4,
        1,
        -9,
        4,
        105,
        -77
      ]
    },
    {
      "code": "2305",
      "name": "全友",
      "market": "TWSE",
      "foreign_daily": [
        -249,
        -176,
        363,
        169,
        -100,
        574
      ],
      "dealer_daily": [
        73,
        -62,
        -9,
        -7,
        1,
        187
      ]
    },
    {
      "code": "6259",
      "name": "百徽",
      "market": "TPEX",
      "foreign_daily": [
        509,
        -24,
        -8,
        167,
        -58,
        -15
      ],
      "dealer_daily": [
        5,
        4,
        9,
        -2,
        8,
        110
      ]
    },
    {
      "code": "1702",
      "name": "南僑",
      "market": "TWSE",
      "foreign_daily": [
        75,
        37,
        155,
        199,
        143,
        -88
      ],
      "dealer_daily": [
        1,
        -6,
        1,
        -2,
        7,
        3
      ]
    },
    {
      "code": "7795",
      "name": "長廣",
      "market": "TWSE",
      "foreign_daily": [
        60,
        276,
        -15,
        -12,
        -17,
        206
      ],
      "dealer_daily": [
        0,
        39,
        -38,
        -5,
        -1,
        46
      ]
    },
    {
      "code": "3265",
      "name": "台星科",
      "market": "TPEX",
      "foreign_daily": [
        1112,
        305,
        -495,
        212,
        -160,
        -497
      ],
      "dealer_daily": [
        95,
        -8,
        -8,
        86,
        -76,
        -43
      ]
    },
    {
      "code": "6231",
      "name": "系微",
      "market": "TPEX",
      "foreign_daily": [
        10,
        403,
        -48,
        109,
        58,
        -66
      ],
      "dealer_daily": [
        8,
        49,
        6,
        13,
        -7,
        -62
      ]
    },
    {
      "code": "3026",
      "name": "禾伸堂",
      "market": "TWSE",
      "foreign_daily": [
        240,
        57,
        492,
        -8,
        -529,
        196
      ],
      "dealer_daily": [
        61,
        22,
        -64,
        79,
        7,
        -42
      ]
    },
    {
      "code": "1529",
      "name": "樂事綠能",
      "market": "TWSE",
      "foreign_daily": [
        186,
        541,
        68,
        -167,
        -49,
        -132
      ],
      "dealer_daily": [
        -1,
        1,
        0,
        1,
        0,
        0
      ]
    },
    {
      "code": "1337",
      "name": "再生-KY",
      "market": "TWSE",
      "foreign_daily": [
        56,
        204,
        -24,
        370,
        -54,
        -111
      ],
      "dealer_daily": [
        4,
        2,
        0,
        0,
        0,
        -2
      ]
    },
    {
      "code": "5904",
      "name": "寶雅",
      "market": "TPEX",
      "foreign_daily": [
        -11,
        -3,
        198,
        159,
        57,
        35
      ],
      "dealer_daily": [
        0,
        16,
        11,
        -7,
        -6,
        -7
      ]
    },
    {
      "code": "4162",
      "name": "智擎",
      "market": "TPEX",
      "foreign_daily": [
        40,
        -29,
        207,
        228,
        -68,
        43
      ],
      "dealer_daily": [
        0,
        0,
        4,
        7,
        0,
        1
      ]
    },
    {
      "code": "2816",
      "name": "旺旺保",
      "market": "TWSE",
      "foreign_daily": [
        16,
        53,
        248,
        -23,
        31,
        78
      ],
      "dealer_daily": [
        1,
        -1,
        0,
        0,
        2,
        -1
      ]
    },
    {
      "code": "1464",
      "name": "得力",
      "market": "TWSE",
      "foreign_daily": [
        90,
        -37,
        73,
        271,
        288,
        -288
      ],
      "dealer_daily": [
        19,
        0,
        2,
        0,
        0,
        -2
      ]
    },
    {
      "code": "9946",
      "name": "三發地產",
      "market": "TWSE",
      "foreign_daily": [
        14,
        -186,
        258,
        183,
        0,
        114
      ],
      "dealer_daily": [
        12,
        -1,
        1,
        0,
        1,
        -1
      ]
    },
    {
      "code": "6146",
      "name": "耕興",
      "market": "TPEX",
      "foreign_daily": [
        108,
        70,
        16,
        46,
        117,
        22
      ],
      "dealer_daily": [
        2,
        5,
        -2,
        -2,
        17,
        -1
      ]
    },
    {
      "code": "2727",
      "name": "王品",
      "market": "TWSE",
      "foreign_daily": [
        148,
        -27,
        4,
        126,
        182,
        -57
      ],
      "dealer_daily": [
        13,
        -2,
        -9,
        0,
        93,
        1
      ]
    },
    {
      "code": "4961",
      "name": "天鈺",
      "market": "TWSE",
      "foreign_daily": [
        442,
        410,
        -143,
        21,
        9,
        -367
      ],
      "dealer_daily": [
        19,
        10,
        -13,
        3,
        -7,
        -9
      ]
    },
    {
      "code": "2537",
      "name": "聯上發",
      "market": "TWSE",
      "foreign_daily": [
        520,
        -1344,
        -148,
        79,
        402,
        862
      ],
      "dealer_daily": [
        28,
        -11,
        0,
        17,
        -22,
        17
      ]
    },
    {
      "code": "1466",
      "name": "聚隆",
      "market": "TWSE",
      "foreign_daily": [
        246,
        159,
        -8,
        -7,
        13,
        -41
      ],
      "dealer_daily": [
        3,
        -2,
        -1,
        7,
        0,
        -3
      ]
    },
    {
      "code": "6535",
      "name": "順藥",
      "market": "TPEX",
      "foreign_daily": [
        157,
        130,
        90,
        46,
        -43,
        -18
      ],
      "dealer_daily": [
        0,
        0,
        0,
        0,
        0,
        1
      ]
    },
    {
      "code": "2753",
      "name": "八方雲集",
      "market": "TWSE",
      "foreign_daily": [
        113,
        -35,
        4,
        -17,
        223,
        61
      ],
      "dealer_daily": [
        1,
        -1,
        4,
        -1,
        1,
        0
      ]
    },
    {
      "code": "6799",
      "name": "來頡",
      "market": "TWSE",
      "foreign_daily": [
        304,
        -356,
        421,
        -255,
        -29,
        257
      ],
      "dealer_daily": [
        25,
        6,
        -9,
        1,
        1,
        -3
      ]
    },
    {
      "code": "2059",
      "name": "川湖",
      "market": "TWSE",
      "foreign_daily": [
        25,
        124,
        -29,
        73,
        127,
        22
      ],
      "dealer_daily": [
        1,
        -9,
        3,
        10,
        1,
        6
      ]
    },
    {
      "code": "1563",
      "name": "巧新",
      "market": "TWSE",
      "foreign_daily": [
        -424,
        138,
        1980,
        -1641,
        -9,
        296
      ],
      "dealer_daily": [
        8,
        -6,
        -8,
        2,
        3,
        4
      ]
    },
    {
      "code": "4536",
      "name": "拓凱",
      "market": "TWSE",
      "foreign_daily": [
        25,
        87,
        44,
        60,
        152,
        -33
      ],
      "dealer_daily": [
        0,
        1,
        1,
        1,
        -1,
        0
      ]
    },
    {
      "code": "2221",
      "name": "大甲",
      "market": "TPEX",
      "foreign_daily": [
        -3,
        521,
        114,
        -18,
        -266,
        -32
      ],
      "dealer_daily": [
        0,
        6,
        -6,
        0,
        0,
        2
      ]
    },
    {
      "code": "2739",
      "name": "寒舍",
      "market": "TWSE",
      "foreign_daily": [
        50,
        4,
        73,
        66,
        180,
        -68
      ],
      "dealer_daily": [
        19,
        3,
        0,
        0,
        -3,
        -1
      ]
    },
    {
      "code": "2434",
      "name": "統懋",
      "market": "TWSE",
      "foreign_daily": [
        5,
        68,
        107,
        -17,
        -118,
        249
      ],
      "dealer_daily": [
        -1,
        0,
        9,
        -9,
        0,
        4
      ]
    },
    {
      "code": "2462",
      "name": "良得電",
      "market": "TWSE",
      "foreign_daily": [
        175,
        52,
        311,
        -282,
        49,
        -12
      ],
      "dealer_daily": [
        4,
        -4,
        1,
        -1,
        -1,
        2
      ]
    },
    {
      "code": "8438",
      "name": "昶昕",
      "market": "TWSE",
      "foreign_daily": [
        92,
        -112,
        231,
        308,
        -208,
        -50
      ],
      "dealer_daily": [
        26,
        0,
        17,
        7,
        -9,
        -11
      ]
    },
    {
      "code": "8213",
      "name": "志超",
      "market": "TWSE",
      "foreign_daily": [
        199,
        -48,
        -36,
        175,
        96,
        -127
      ],
      "dealer_daily": [
        2,
        -5,
        10,
        6,
        0,
        30
      ]
    },
    {
      "code": "5278",
      "name": "尚凡*",
      "market": "TPEX",
      "foreign_daily": [
        -74,
        46,
        60,
        39,
        13,
        169
      ],
      "dealer_daily": [
        20,
        0,
        0,
        -1,
        0,
        4
      ]
    },
    {
      "code": "2032",
      "name": "新鋼",
      "market": "TWSE",
      "foreign_daily": [
        150,
        249,
        -82,
        -31,
        30,
        -73
      ],
      "dealer_daily": [
        3,
        -3,
        3,
        1,
        0,
        10
      ]
    },
    {
      "code": "8038",
      "name": "長園科",
      "market": "TPEX",
      "foreign_daily": [
        78,
        185,
        -47,
        51,
        105,
        -130
      ],
      "dealer_daily": [
        0,
        0,
        0,
        0,
        0,
        1
      ]
    },
    {
      "code": "1446",
      "name": "宏和",
      "market": "TWSE",
      "foreign_daily": [
        60,
        -7,
        126,
        68,
        7,
        -15
      ],
      "dealer_daily": [
        1,
        -3,
        6,
        0,
        1,
        -1
      ]
    },
    {
      "code": "3066",
      "name": "李洲",
      "market": "TPEX",
      "foreign_daily": [
        61,
        182,
        221,
        -241,
        -34,
        50
      ],
      "dealer_daily": [
        0,
        0,
        11,
        -11,
        -1,
        36
      ]
    },
    {
      "code": "2707",
      "name": "晶華",
      "market": "TWSE",
      "foreign_daily": [
        -29,
        -17,
        69,
        102,
        93,
        18
      ],
      "dealer_daily": [
        0,
        1,
        1,
        16,
        9,
        -1
      ]
    },
    {
      "code": "1570",
      "name": "力肯",
      "market": "TPEX",
      "foreign_daily": [
        39,
        36,
        5,
        126,
        10,
        17
      ],
      "dealer_daily": [
        0,
        0,
        0,
        -1,
        7,
        0
      ]
    },
    {
      "code": "1909",
      "name": "榮成",
      "market": "TWSE",
      "foreign_daily": [
        2108,
        240,
        -1322,
        16,
        -1018,
        205
      ],
      "dealer_daily": [
        11,
        53,
        11,
        19,
        20,
        17
      ]
    },
    {
      "code": "8183",
      "name": "精星",
      "market": "TPEX",
      "foreign_daily": [
        -38,
        303,
        -152,
        -73,
        4,
        179
      ],
      "dealer_daily": [
        0,
        0,
        -21,
        -2,
        19,
        8
      ]
    },
    {
      "code": "2608",
      "name": "嘉里大榮",
      "market": "TWSE",
      "foreign_daily": [
        8,
        -19,
        310,
        21,
        36,
        -138
      ],
      "dealer_daily": [
        19,
        -12,
        1,
        2,
        9,
        -3
      ]
    },
    {
      "code": "2211",
      "name": "長榮鋼",
      "market": "TWSE",
      "foreign_daily": [
        96,
        -85,
        63,
        148,
        64,
        -69
      ],
      "dealer_daily": [
        37,
        30,
        2,
        2,
        5,
        -5
      ]
    },
    {
      "code": "2038",
      "name": "海光",
      "market": "TWSE",
      "foreign_daily": [
        126,
        226,
        -117,
        -26,
        5,
        0
      ],
      "dealer_daily": [
        -1,
        -2,
        0,
        3,
        0,
        12
      ]
    },
    {
      "code": "3583",
      "name": "辛耘",
      "market": "TWSE",
      "foreign_daily": [
        230,
        -246,
        295,
        -203,
        -18,
        154
      ],
      "dealer_daily": [
        66,
        19,
        14,
        31,
        26,
        -42
      ]
    },
    {
      "code": "3228",
      "name": "金麗科",
      "market": "TPEX",
      "foreign_daily": [
        14,
        41,
        -63,
        45,
        -63,
        234
      ],
      "dealer_daily": [
        -2,
        17,
        -13,
        -2,
        -9,
        10
      ]
    },
    {
      "code": "2349",
      "name": "錸德",
      "market": "TWSE",
      "foreign_daily": [
        1491,
        1170,
        504,
        -130,
        -687,
        -2143
      ],
      "dealer_daily": [
        20,
        -5,
        -1,
        5,
        -5,
        0
      ]
    },
    {
      "code": "6104",
      "name": "創惟",
      "market": "TPEX",
      "foreign_daily": [
        1430,
        1030,
        123,
        -311,
        -777,
        -1290
      ],
      "dealer_daily": [
        80,
        89,
        -27,
        -14,
        -19,
        -106
      ]
    },
    {
      "code": "6552",
      "name": "易華電",
      "market": "TWSE",
      "foreign_daily": [
        -65,
        168,
        60,
        10,
        85,
        -55
      ],
      "dealer_daily": [
        -1,
        -1,
        6,
        0,
        0,
        6
      ]
    },
    {
      "code": "1762",
      "name": "中化生",
      "market": "TWSE",
      "foreign_daily": [
        43,
        85,
        114,
        24,
        4,
        -69
      ],
      "dealer_daily": [
        3,
        1,
        2,
        -8,
        3,
        3
      ]
    },
    {
      "code": "2745",
      "name": "五福",
      "market": "TPEX",
      "foreign_daily": [
        44,
        -20,
        -11,
        15,
        117,
        56
      ],
      "dealer_daily": [
        3,
        0,
        0,
        1,
        63,
        38
      ]
    },
    {
      "code": "2516",
      "name": "新建",
      "market": "TWSE",
      "foreign_daily": [
        -11,
        111,
        121,
        26,
        -41,
        -7
      ],
      "dealer_daily": [
        1,
        -2,
        0,
        0,
        0,
        5
      ]
    },
    {
      "code": "3441",
      "name": "聯一光",
      "market": "TPEX",
      "foreign_daily": [
        -514,
        88,
        368,
        52,
        201,
        -2
      ],
      "dealer_daily": [
        -40,
        0,
        -1,
        248,
        12,
        -125
      ]
    },
    {
      "code": "1786",
      "name": "科妍",
      "market": "TWSE",
      "foreign_daily": [
        66,
        96,
        64,
        51,
        -28,
        -58
      ],
      "dealer_daily": [
        0,
        5,
        0,
        -2,
        0,
        0
      ]
    },
    {
      "code": "2748",
      "name": "雲品",
      "market": "TWSE",
      "foreign_daily": [
        -5,
        13,
        17,
        50,
        40,
        76
      ],
      "dealer_daily": [
        0,
        0,
        1,
        -1,
        0,
        2
      ]
    },
    {
      "code": "6756",
      "name": "威鋒電子",
      "market": "TWSE",
      "foreign_daily": [
        89,
        195,
        44,
        0,
        -2,
        -140
      ],
      "dealer_daily": [
        1,
        -2,
        4,
        -1,
        -8,
        7
      ]
    },
    {
      "code": "8227",
      "name": "巨有科技",
      "market": "TPEX",
      "foreign_daily": [
        -134,
        -115,
        59,
        49,
        -44,
        364
      ],
      "dealer_daily": [
        17,
        88,
        -58,
        34,
        -63,
        58
      ]
    },
    {
      "code": "4109",
      "name": "加捷生醫",
      "market": "TPEX",
      "foreign_daily": [
        26,
        -14,
        -21,
        30,
        -4,
        159
      ],
      "dealer_daily": [
        0,
        0,
        1,
        0,
        0,
        0
      ]
    },
    {
      "code": "2062",
      "name": "橋椿",
      "market": "TWSE",
      "foreign_daily": [
        -36,
        156,
        94,
        20,
        95,
        -154
      ],
      "dealer_daily": [
        0,
        0,
        11,
        0,
        0,
        -1
      ]
    },
    {
      "code": "3716",
      "name": "中化控股",
      "market": "TWSE",
      "foreign_daily": [
        6,
        -45,
        138,
        76,
        73,
        -76
      ],
      "dealer_daily": [
        17,
        -3,
        0,
        0,
        0,
        0
      ]
    },
    {
      "code": "6732",
      "name": "昇佳電子",
      "market": "TPEX",
      "foreign_daily": [
        49,
        45,
        55,
        40,
        56,
        -78
      ],
      "dealer_daily": [
        -1,
        0,
        3,
        0,
        0,
        1
      ]
    },
    {
      "code": "1776",
      "name": "展宇",
      "market": "TWSE",
      "foreign_daily": [
        6,
        147,
        -48,
        19,
        37,
        -3
      ],
      "dealer_daily": [
        -1,
        9,
        3,
        -1,
        3,
        -4
      ]
    },
    {
      "code": "2849",
      "name": "安泰銀",
      "market": "TWSE",
      "foreign_daily": [
        -21,
        34,
        153,
        25,
        57,
        -93
      ],
      "dealer_daily": [
        4,
        -13,
        0,
        0,
        24,
        -9
      ]
    },
    {
      "code": "6229",
      "name": "研通",
      "market": "TPEX",
      "foreign_daily": [
        196,
        50,
        -34,
        -24,
        -22,
        -12
      ],
      "dealer_daily": [
        0,
        0,
        0,
        14,
        1,
        0
      ]
    },
    {
      "code": "5392",
      "name": "能率",
      "market": "TPEX",
      "foreign_daily": [
        -885,
        -99,
        148,
        -665,
        702,
        952
      ],
      "dealer_daily": [
        -2,
        36,
        -20,
        -15,
        202,
        105
      ]
    },
    {
      "code": "8299",
      "name": "群聯",
      "market": "TPEX",
      "foreign_daily": [
        708,
        -901,
        -247,
        528,
        -111,
        174
      ],
      "dealer_daily": [
        254,
        117,
        -58,
        -6,
        13,
        -165
      ]
    },
    {
      "code": "4566",
      "name": "時碩工業",
      "market": "TWSE",
      "foreign_daily": [
        188,
        48,
        -52,
        44,
        65,
        -149
      ],
      "dealer_daily": [
        0,
        0,
        0,
        1,
        0,
        0
      ]
    },
    {
      "code": "5292",
      "name": "華懋",
      "market": "TWSE",
      "foreign_daily": [
        33,
        22,
        22,
        46,
        28,
        -10
      ],
      "dealer_daily": [
        1,
        6,
        1,
        -3,
        1,
        -2
      ]
    },
    {
      "code": "1103",
      "name": "嘉泥",
      "market": "TWSE",
      "foreign_daily": [
        -54,
        140,
        21,
        33,
        81,
        -84
      ],
      "dealer_daily": [
        0,
        -9,
        2,
        -1,
        10,
        22
      ]
    },
    {
      "code": "5432",
      "name": "新門",
      "market": "TPEX",
      "foreign_daily": [
        112,
        -12,
        -7,
        64,
        -90,
        64
      ],
      "dealer_daily": [
        3,
        -1,
        -1,
        3,
        0,
        1
      ]
    },
    {
      "code": "1615",
      "name": "大山",
      "market": "TWSE",
      "foreign_daily": [
        28,
        47,
        0,
        38,
        82,
        -70
      ],
      "dealer_daily": [
        0,
        0,
        0,
        0,
        0,
        6
      ]
    },
    {
      "code": "8499",
      "name": "鼎炫-KY",
      "market": "TWSE",
      "foreign_daily": [
        6,
        76,
        11,
        -24,
        19,
        36
      ],
      "dealer_daily": [
        0,
        10,
        2,
        -1,
        0,
        -4
      ]
    },
    {
      "code": "3141",
      "name": "晶宏",
      "market": "TPEX",
      "foreign_daily": [
        272,
        208,
        -316,
        62,
        0,
        -103
      ],
      "dealer_daily": [
        9,
        69,
        -18,
        2,
        0,
        -6
      ]
    },
    {
      "code": "6122",
      "name": "擎邦",
      "market": "TPEX",
      "foreign_daily": [
        5,
        89,
        -14,
        31,
        58,
        -46
      ],
      "dealer_daily": [
        1,
        0,
        0,
        9,
        1,
        -4
      ]
    },
    {
      "code": "6712",
      "name": "長聖",
      "market": "TPEX",
      "foreign_daily": [
        -17,
        -1,
        -99,
        353,
        7,
        -121
      ],
      "dealer_daily": [
        0,
        0,
        1,
        8,
        -3,
        2
      ]
    },
    {
      "code": "7769",
      "name": "鴻勁",
      "market": "TWSE",
      "foreign_daily": [
        -270,
        238,
        108,
        50,
        41,
        -48
      ],
      "dealer_daily": [
        0,
        4,
        -1,
        -1,
        5,
        -6
      ]
    },
    {
      "code": "2906",
      "name": "高林",
      "market": "TWSE",
      "foreign_daily": [
        -1,
        -24,
        -1,
        12,
        21,
        109
      ],
      "dealer_daily": [
        -6,
        -1,
        6,
        0,
        2,
        4
      ]
    },
    {
      "code": "2206",
      "name": "三陽工業",
      "market": "TWSE",
      "foreign_daily": [
        -327,
        -200,
        198,
        136,
        361,
        -56
      ],
      "dealer_daily": [
        0,
        0,
        9,
        1,
        0,
        -5
      ]
    },
    {
      "code": "8045",
      "name": "達運光電",
      "market": "TWSE",
      "foreign_daily": [
        -1,
        100,
        -4,
        9,
        3,
        4
      ],
      "dealer_daily": [
        -1,
        0,
        -1,
        0,
        0,
        3
      ]
    },
    {
      "code": "1340",
      "name": "勝悅-KY",
      "market": "TWSE",
      "foreign_daily": [
        76,
        -18,
        -10,
        34,
        4,
        24
      ],
      "dealer_daily": [
        4,
        1,
        0,
        0,
        0,
        -3
      ]
    },
    {
      "code": "6530",
      "name": "創威",
      "market": "TPEX",
      "foreign_daily": [
        85,
        90,
        -231,
        -3,
        127,
        41
      ],
      "dealer_daily": [
        0,
        0,
        4,
        0,
        0,
        0
      ]
    },
    {
      "code": "1531",
      "name": "高林股",
      "market": "TWSE",
      "foreign_daily": [
        10,
        14,
        163,
        17,
        -119,
        23
      ],
      "dealer_daily": [
        -1,
        0,
        4,
        0,
        0,
        0
      ]
    },
    {
      "code": "2506",
      "name": "太設",
      "market": "TWSE",
      "foreign_daily": [
        4,
        15,
        45,
        27,
        4,
        12
      ],
      "dealer_daily": [
        0,
        0,
        0,
        0,
        4,
        -2
      ]
    },
    {
      "code": "1735",
      "name": "日勝化",
      "market": "TWSE",
      "foreign_daily": [
        104,
        5,
        -10,
        76,
        -8,
        -62
      ],
      "dealer_daily": [
        -1,
        0,
        -1,
        0,
        0,
        3
      ]
    },
    {
      "code": "3686",
      "name": "達能",
      "market": "TWSE",
      "foreign_daily": [
        12,
        94,
        -14,
        18,
        66,
        -71
      ],
      "dealer_daily": [
        -1,
        0,
        0,
        0,
        0,
        2
      ]
    },
    {
      "code": "1565",
      "name": "精華",
      "market": "TPEX",
      "foreign_daily": [
        -11,
        39,
        46,
        29,
        34,
        -37
      ],
      "dealer_daily": [
        -3,
        4,
        0,
        0,
        16,
        1
      ]
    },
    {
      "code": "6510",
      "name": "精測",
      "market": "TPEX",
      "foreign_daily": [
        -50,
        -95,
        297,
        -4,
        -4,
        -44
      ],
      "dealer_daily": [
        5,
        -8,
        8,
        5,
        5,
        -13
      ]
    },
    {
      "code": "5272",
      "name": "笙科",
      "market": "TPEX",
      "foreign_daily": [
        44,
        78,
        8,
        51,
        -71,
        -16
      ],
      "dealer_daily": [
        0,
        0,
        0,
        0,
        0,
        1
      ]
    },
    {
      "code": "5603",
      "name": "陸海",
      "market": "TPEX",
      "foreign_daily": [
        21,
        50,
        15,
        8,
        18,
        -19
      ],
      "dealer_daily": [
        0,
        0,
        0,
        0,
        0,
        1
      ]
    },
    {
      "code": "4933",
      "name": "友輝",
      "market": "TPEX",
      "foreign_daily": [
        -78,
        107,
        -17,
        1,
        30,
        49
      ],
      "dealer_daily": [
        0,
        0,
        -2,
        0,
        0,
        12
      ]
    },
    {
      "code": "2546",
      "name": "根基",
      "market": "TWSE",
      "foreign_daily": [
        30,
        -18,
        35,
        14,
        -2,
        26
      ],
      "dealer_daily": [
        7,
        7,
        -1,
        8,
        -8,
        -12
      ]
    },
    {
      "code": "2705",
      "name": "六福",
      "market": "TWSE",
      "foreign_daily": [
        62,
        -41,
        29,
        14,
        25,
        -5
      ],
      "dealer_daily": [
        -2,
        0,
        0,
        0,
        2,
        2
      ]
    },
    {
      "code": "2013",
      "name": "中鋼構",
      "market": "TWSE",
      "foreign_daily": [
        52,
        -13,
        15,
        44,
        -69,
        55
      ],
      "dealer_daily": [
        -1,
        -1,
        0,
        17,
        53,
        12
      ]
    },
    {
      "code": "6958",
      "name": "日盛台駿",
      "market": "TWSE",
      "foreign_daily": [
        1,
        14,
        39,
        42,
        2,
        -15
      ],
      "dealer_daily": [
        15,
        -2,
        0,
        4,
        1,
        -3
      ]
    },
    {
      "code": "4923",
      "name": "力士",
      "market": "TPEX",
      "foreign_daily": [
        -94,
        230,
        -30,
        -33,
        -28,
        38
      ],
      "dealer_daily": [
        2,
        -5,
        -3,
        0,
        0,
        120
      ]
    },
    {
      "code": "5306",
      "name": "桂盟",
      "market": "TWSE",
      "foreign_daily": [
        -26,
        68,
        28,
        -1,
        -10,
        20
      ],
      "dealer_daily": [
        1,
        1,
        10,
        1,
        4,
        -2
      ]
    },
    {
      "code": "5344",
      "name": "立衛",
      "market": "TPEX",
      "foreign_daily": [
        -1,
        164,
        -111,
        5,
        19,
        2
      ],
      "dealer_daily": [
        0,
        0,
        0,
        0,
        0,
        2
      ]
    },
    {
      "code": "4130",
      "name": "健亞",
      "market": "TPEX",
      "foreign_daily": [
        14,
        19,
        7,
        23,
        14,
        0
      ],
      "dealer_daily": [
        0,
        0,
        0,
        1,
        1,
        0
      ]
    },
    {
      "code": "1437",
      "name": "勤益控",
      "market": "TWSE",
      "foreign_daily": [
        -24,
        26,
        22,
        12,
        44,
        -4
      ],
      "dealer_daily": [
        6,
        -4,
        0,
        0,
        3,
        -2
      ]
    },
    {
      "code": "1201",
      "name": "味全",
      "market": "TWSE",
      "foreign_daily": [
        35,
        -148,
        86,
        192,
        186,
        -280
      ],
      "dealer_daily": [
        0,
        -9,
        1,
        -1,
        5,
        21
      ]
    },
    {
      "code": "6894",
      "name": "衛司特",
      "market": "TPEX",
      "foreign_daily": [
        31,
        60,
        13,
        2,
        3,
        -40
      ],
      "dealer_daily": [
        3,
        5,
        -1,
        0,
        0,
        0
      ]
    },
    {
      "code": "6996",
      "name": "力領科技",
      "market": "TPEX",
      "foreign_daily": [
        4,
        37,
        73,
        12,
        10,
        -68
      ],
      "dealer_daily": [
        0,
        0,
        4,
        0,
        0,
        2
      ]
    },
    {
      "code": "2889",
      "name": "國票金",
      "market": "TWSE",
      "foreign_daily": [
        -368,
        -2319,
        2368,
        -1264,
        1304,
        344
      ],
      "dealer_daily": [
        30,
        -4,
        8,
        -5,
        32,
        -22
      ]
    },
    {
      "code": "9924",
      "name": "福興",
      "market": "TWSE",
      "foreign_daily": [
        29,
        -16,
        2,
        77,
        23,
        -54
      ],
      "dealer_daily": [
        0,
        -2,
        0,
        0,
        1,
        2
      ]
    },
    {
      "code": "1720",
      "name": "生達",
      "market": "TWSE",
      "foreign_daily": [
        -30,
        -131,
        91,
        126,
        65,
        -67
      ],
      "dealer_daily": [
        6,
        0,
        -1,
        -1,
        -2,
        5
      ]
    },
    {
      "code": "6921",
      "name": "嘉雨思-創",
      "market": "TWSE",
      "foreign_daily": [
        42,
        11,
        13,
        6,
        8,
        -28
      ],
      "dealer_daily": [
        3,
        3,
        0,
        1,
        2,
        3
      ]
    },
    {
      "code": "6792",
      "name": "詠業",
      "market": "TWSE",
      "foreign_daily": [
        40,
        -32,
        7,
        -27,
        27,
        36
      ],
      "dealer_daily": [
        0,
        1,
        -1,
        0,
        0,
        2
      ]
    },
    {
      "code": "3268",
      "name": "海德威",
      "market": "TPEX",
      "foreign_daily": [
        49,
        46,
        -88,
        28,
        -18,
        33
      ],
      "dealer_daily": [
        0,
        1,
        0,
        0,
        0,
        0
      ]
    },
    {
      "code": "8437",
      "name": "大地-KY",
      "market": "TPEX",
      "foreign_daily": [
        20,
        24,
        -17,
        18,
        17,
        -12
      ],
      "dealer_daily": [
        2,
        0,
        0,
        0,
        0,
        0
      ]
    },
    {
      "code": "1725",
      "name": "元禎",
      "market": "TWSE",
      "foreign_daily": [
        133,
        -18,
        14,
        50,
        -61,
        -69
      ],
      "dealer_daily": [
        7,
        3,
        -10,
        0,
        3,
        3
      ]
    },
    {
      "code": "3024",
      "name": "憶聲",
      "market": "TWSE",
      "foreign_daily": [
        -319,
        441,
        61,
        30,
        -18,
        -146
      ],
      "dealer_daily": [
        -14,
        16,
        13,
        -1,
        -3,
        -7
      ]
    },
    {
      "code": "2706",
      "name": "第一店",
      "market": "TWSE",
      "foreign_daily": [
        2,
        10,
        46,
        22,
        17,
        -51
      ],
      "dealer_daily": [
        0,
        -3,
        8,
        0,
        0,
        12
      ]
    },
    {
      "code": "4155",
      "name": "訊映",
      "market": "TWSE",
      "foreign_daily": [
        -44,
        -64,
        -9,
        119,
        -27,
        71
      ],
      "dealer_daily": [
        3,
        2,
        19,
        3,
        0,
        -1
      ]
    },
    {
      "code": "1732",
      "name": "毛寶",
      "market": "TWSE",
      "foreign_daily": [
        18,
        13,
        -7,
        18,
        16,
        -15
      ],
      "dealer_daily": [
        0,
        0,
        0,
        0,
        0,
        1
      ]
    },
    {
      "code": "4104",
      "name": "佳醫",
      "market": "TWSE",
      "foreign_daily": [
        -31,
        -43,
        75,
        14,
        100,
        -72
      ],
      "dealer_daily": [
        3,
        -1,
        1,
        0,
        0,
        -1
      ]
    },
    {
      "code": "3685",
      "name": "元創精密",
      "market": "TPEX",
      "foreign_daily": [
        -128,
        22,
        221,
        -60,
        -11,
        -1
      ],
      "dealer_daily": [
        4,
        -4,
        0,
        8,
        0,
        0
      ]
    },
    {
      "code": "6753",
      "name": "龍德造船",
      "market": "TWSE",
      "foreign_daily": [
        110,
        138,
        -89,
        -44,
        -87,
        13
      ],
      "dealer_daily": [
        75,
        156,
        -5,
        -11,
        -13,
        1
      ]
    },
    {
      "code": "2509",
      "name": "全坤建",
      "market": "TWSE",
      "foreign_daily": [
        13,
        -92,
        54,
        55,
        4,
        7
      ],
      "dealer_daily": [
        0,
        5,
        1,
        -1,
        0,
        -1
      ]
    },
    {
      "code": "1473",
      "name": "台南",
      "market": "TWSE",
      "foreign_daily": [
        4,
        -36,
        30,
        47,
        29,
        -37
      ],
      "dealer_daily": [
        2,
        0,
        0,
        0,
        0,
        -1
      ]
    },
    {
      "code": "2433",
      "name": "互盛電",
      "market": "TWSE",
      "foreign_daily": [
        1,
        5,
        15,
        45,
        -10,
        -21
      ],
      "dealer_daily": [
        -2,
        -1,
        2,
        0,
        1,
        1
      ]
    },
    {
      "code": "1906",
      "name": "寶隆",
      "market": "TWSE",
      "foreign_daily": [
        -9,
        31,
        17,
        8,
        16,
        -28
      ],
      "dealer_daily": [
        1,
        5,
        0,
        -2,
        1,
        -4
      ]
    },
    {
      "code": "1475",
      "name": "業旺",
      "market": "TWSE",
      "foreign_daily": [
        18,
        4,
        15,
        1,
        0,
        -4
      ],
      "dealer_daily": [
        2,
        -2,
        1,
        0,
        1,
        -1
      ]
    },
    {
      "code": "1339",
      "name": "昭輝",
      "market": "TWSE",
      "foreign_daily": [
        118,
        -32,
        -3,
        -2,
        -25,
        -23
      ],
      "dealer_daily": [
        1,
        -1,
        0,
        1,
        2,
        0
      ]
    },
    {
      "code": "5263",
      "name": "智崴",
      "market": "TPEX",
      "foreign_daily": [
        -8,
        -12,
        1,
        98,
        10,
        -56
      ],
      "dealer_daily": [
        5,
        5,
        -2,
        4,
        0,
        5
      ]
    },
    {
      "code": "7722",
      "name": "LINEPAY",
      "market": "TWSE",
      "foreign_daily": [
        35,
        -32,
        2,
        22,
        16,
        -12
      ],
      "dealer_daily": [
        0,
        -1,
        0,
        0,
        9,
        -6
      ]
    },
    {
      "code": "2008",
      "name": "高興昌",
      "market": "TWSE",
      "foreign_daily": [
        1,
        15,
        6,
        5,
        5,
        -2
      ],
      "dealer_daily": [
        2,
        -3,
        1,
        -2,
        5,
        -1
      ]
    },
    {
      "code": "3516",
      "name": "亞帝歐",
      "market": "TPEX",
      "foreign_daily": [
        -61,
        -1,
        11,
        5,
        23,
        53
      ],
      "dealer_daily": [
        0,
        0,
        14,
        0,
        -2,
        0
      ]
    },
    {
      "code": "3652",
      "name": "精聯",
      "market": "TWSE",
      "foreign_daily": [
        95,
        -321,
        -131,
        19,
        211,
        156
      ],
      "dealer_daily": [
        -3,
        9,
        -4,
        0,
        -5,
        5
      ]
    },
    {
      "code": "3713",
      "name": "新晶投控",
      "market": "TPEX",
      "foreign_daily": [
        22,
        -14,
        13,
        13,
        0,
        -6
      ],
      "dealer_daily": [
        0,
        0,
        0,
        9,
        0,
        0
      ]
    },
    {
      "code": "6588",
      "name": "東典光電",
      "market": "TPEX",
      "foreign_daily": [
        4,
        85,
        -8,
        -76,
        -92,
        113
      ],
      "dealer_daily": [
        0,
        0,
        1,
        0,
        1,
        -1
      ]
    },
    {
      "code": "7715",
      "name": "裕山",
      "market": "TPEX",
      "foreign_daily": [
        67,
        -16,
        9,
        10,
        -53,
        9
      ],
      "dealer_daily": [
        2,
        2,
        -3,
        0,
        0,
        0
      ]
    },
    {
      "code": "2373",
      "name": "震旦行",
      "market": "TWSE",
      "foreign_daily": [
        -7,
        -1,
        37,
        2,
        -3,
        -3
      ],
      "dealer_daily": [
        0,
        0,
        0,
        0,
        0,
        1
      ]
    },
    {
      "code": "4572",
      "name": "駐龍",
      "market": "TWSE",
      "foreign_daily": [
        8,
        13,
        9,
        3,
        -3,
        -6
      ],
      "dealer_daily": [
        0,
        -1,
        0,
        0,
        0,
        2
      ]
    },
    {
      "code": "5546",
      "name": "永固-KY",
      "market": "TWSE",
      "foreign_daily": [
        0,
        3,
        8,
        0,
        13,
        0
      ],
      "dealer_daily": [
        1,
        0,
        0,
        0,
        1,
        -1
      ]
    },
    {
      "code": "6914",
      "name": "阜爾運通",
      "market": "TWSE",
      "foreign_daily": [
        8,
        -3,
        0,
        9,
        21,
        -13
      ],
      "dealer_daily": [
        3,
        -1,
        0,
        0,
        1,
        3
      ]
    },
    {
      "code": "1472",
      "name": "三洋實業",
      "market": "TWSE",
      "foreign_daily": [
        -15,
        1,
        -3,
        2,
        5,
        32
      ],
      "dealer_daily": [
        -1,
        3,
        0,
        0,
        0,
        -1
      ]
    },
    {
      "code": "6585",
      "name": "鼎基",
      "market": "TWSE",
      "foreign_daily": [
        14,
        93,
        -40,
        -194,
        -54,
        202
      ],
      "dealer_daily": [
        -1,
        16,
        2,
        0,
        -1,
        0
      ]
    },
    {
      "code": "6870",
      "name": "騰雲",
      "market": "TPEX",
      "foreign_daily": [
        -20,
        -8,
        27,
        -2,
        0,
        24
      ],
      "dealer_daily": [
        -6,
        3,
        6,
        1,
        1,
        -1
      ]
    },
    {
      "code": "1533",
      "name": "車王電",
      "market": "TWSE",
      "foreign_daily": [
        41,
        4,
        -17,
        -6,
        -3,
        1
      ],
      "dealer_daily": [
        8,
        8,
        -1,
        -1,
        1,
        -5
      ]
    },
    {
      "code": "5519",
      "name": "隆大",
      "market": "TWSE",
      "foreign_daily": [
        -138,
        -382,
        22,
        34,
        150,
        334
      ],
      "dealer_daily": [
        -16,
        -2,
        0,
        116,
        146,
        -1
      ]
    },
    {
      "code": "6789",
      "name": "采鈺",
      "market": "TWSE",
      "foreign_daily": [
        654,
        -717,
        183,
        -292,
        81,
        110
      ],
      "dealer_daily": [
        39,
        67,
        0,
        25,
        30,
        -99
      ]
    },
    {
      "code": "1760",
      "name": "寶齡富錦",
      "market": "TWSE",
      "foreign_daily": [
        -20,
        43,
        35,
        22,
        -19,
        -42
      ],
      "dealer_daily": [
        7,
        2,
        0,
        0,
        1,
        -2
      ]
    },
    {
      "code": "6419",
      "name": "京晨科",
      "market": "TPEX",
      "foreign_daily": [
        78,
        -53,
        103,
        -47,
        -74,
        9
      ],
      "dealer_daily": [
        -3,
        1,
        0,
        2,
        0,
        5
      ]
    },
    {
      "code": "6763",
      "name": "綠界科技*",
      "market": "TPEX",
      "foreign_daily": [
        126,
        107,
        -74,
        -2,
        -43,
        -98
      ],
      "dealer_daily": [
        2,
        -1,
        0,
        1,
        14,
        -1
      ]
    },
    {
      "code": "6183",
      "name": "關貿",
      "market": "TWSE",
      "foreign_daily": [
        8,
        -4,
        12,
        -1,
        15,
        -16
      ],
      "dealer_daily": [
        0,
        0,
        2,
        -1,
        1,
        4
      ]
    },
    {
      "code": "4148",
      "name": "全宇生技-KY",
      "market": "TWSE",
      "foreign_daily": [
        3,
        -1,
        1,
        20,
        -7,
        -2
      ],
      "dealer_daily": [
        -1,
        0,
        1,
        0,
        -1,
        3
      ]
    },
    {
      "code": "1817",
      "name": "凱撒衛",
      "market": "TWSE",
      "foreign_daily": [
        0,
        -1,
        1,
        7,
        -1,
        7
      ],
      "dealer_daily": [
        0,
        0,
        0,
        0,
        0,
        4
      ]
    },
    {
      "code": "2910",
      "name": "統領",
      "market": "TWSE",
      "foreign_daily": [
        2,
        2,
        3,
        4,
        0,
        1
      ],
      "dealer_daily": [
        1,
        -1,
        0,
        0,
        0,
        1
      ]
    },
    {
      "code": "3288",
      "name": "點晶",
      "market": "TPEX",
      "foreign_daily": [
        0,
        36,
        -28,
        2,
        -10,
        11
      ],
      "dealer_daily": [
        0,
        0,
        0,
        0,
        0,
        3
      ]
    },
    {
      "code": "4556",
      "name": "旭然",
      "market": "TPEX",
      "foreign_daily": [
        -2,
        12,
        11,
        -4,
        -3,
        -3
      ],
      "dealer_daily": [
        0,
        0,
        0,
        0,
        -1,
        2
      ]
    },
    {
      "code": "3167",
      "name": "大量",
      "market": "TWSE",
      "foreign_daily": [
        -10,
        -45,
        60,
        2,
        25,
        -22
      ],
      "dealer_daily": [
        29,
        36,
        -1,
        28,
        -16,
        -8
      ]
    },
    {
      "code": "6952",
      "name": "大武山",
      "market": "TWSE",
      "foreign_daily": [
        4,
        1,
        5,
        12,
        -1,
        -11
      ],
      "dealer_daily": [
        3,
        0,
        0,
        0,
        0,
        -1
      ]
    },
    {
      "code": "6908",
      "name": "宏碁遊戲-創",
      "market": "TWSE",
      "foreign_daily": [
        0,
        0,
        0,
        0,
        0,
        9
      ],
      "dealer_daily": [
        0,
        0,
        0,
        0,
        0,
        1
      ]
    },
    {
      "code": "1454",
      "name": "台富",
      "market": "TWSE",
      "foreign_daily": [
        0,
        3,
        9,
        7,
        -1,
        -9
      ],
      "dealer_daily": [
        0,
        -3,
        0,
        2,
        1,
        2
      ]
    },
    {
      "code": "4530",
      "name": "宏易",
      "market": "TPEX",
      "foreign_daily": [
        -1,
        0,
        -1,
        0,
        0,
        11
      ],
      "dealer_daily": [
        0,
        0,
        1,
        0,
        0,
        0
      ]
    },
    {
      "code": "1233",
      "name": "天仁",
      "market": "TWSE",
      "foreign_daily": [
        -2,
        3,
        10,
        3,
        -17,
        11
      ],
      "dealer_daily": [
        2,
        0,
        0,
        0,
        0,
        -1
      ]
    },
    {
      "code": "6464",
      "name": "台數科",
      "market": "TWSE",
      "foreign_daily": [
        -5,
        3,
        11,
        0,
        2,
        -3
      ],
      "dealer_daily": [
        -1,
        1,
        2,
        0,
        0,
        1
      ]
    },
    {
      "code": "9944",
      "name": "新麗",
      "market": "TWSE",
      "foreign_daily": [
        -17,
        11,
        19,
        -4,
        8,
        -9
      ],
      "dealer_daily": [
        2,
        0,
        -1,
        0,
        3,
        -1
      ]
    },
    {
      "code": "6195",
      "name": "詩肯",
      "market": "TPEX",
      "foreign_daily": [
        4,
        0,
        1,
        0,
        6,
        -3
      ],
      "dealer_daily": [
        0,
        0,
        0,
        0,
        0,
        1
      ]
    },
    {
      "code": "2258",
      "name": "鴻華先進-創",
      "market": "TWSE",
      "foreign_daily": [
        148,
        189,
        102,
        329,
        -475,
        -286
      ],
      "dealer_daily": [
        -14,
        -10,
        3,
        15,
        3,
        6
      ]
    },
    {
      "code": "2028",
      "name": "威致",
      "market": "TWSE",
      "foreign_daily": [
        31,
        4,
        101,
        -9,
        -9,
        -111
      ],
      "dealer_daily": [
        0,
        -8,
        0,
        14,
        0,
        -1
      ]
    },
    {
      "code": "6504",
      "name": "南六",
      "market": "TWSE",
      "foreign_daily": [
        12,
        9,
        -9,
        14,
        -8,
        -11
      ],
      "dealer_daily": [
        0,
        0,
        0,
        3,
        0,
        0
      ]
    },
    {
      "code": "6906",
      "name": "現觀科",
      "market": "TWSE",
      "foreign_daily": [
        -22,
        -12,
        -17,
        59,
        25,
        -26
      ],
      "dealer_daily": [
        0,
        0,
        0,
        0,
        -1,
        2
      ]
    },
    {
      "code": "9929",
      "name": "秋雨",
      "market": "TWSE",
      "foreign_daily": [
        0,
        6,
        2,
        3,
        -2,
        -4
      ],
      "dealer_daily": [
        1,
        -1,
        0,
        -1,
        1,
        4
      ]
    },
    {
      "code": "2024",
      "name": "志聯",
      "market": "TWSE",
      "foreign_daily": [
        -1,
        4,
        13,
        -2,
        -4,
        -5
      ],
      "dealer_daily": [
        1,
        1,
        0,
        0,
        1,
        -1
      ]
    },
    {
      "code": "4706",
      "name": "大恭",
      "market": "TPEX",
      "foreign_daily": [
        -1,
        2,
        0,
        0,
        2,
        2
      ],
      "dealer_daily": [
        0,
        0,
        0,
        0,
        0,
        1
      ]
    },
    {
      "code": "7842",
      "name": "天能綠電",
      "market": "TPEX",
      "foreign_daily": [
        6,
        -2,
        -2,
        5,
        0,
        -2
      ],
      "dealer_daily": [
        0,
        0,
        0,
        0,
        0,
        2
      ]
    },
    {
      "code": "2227",
      "name": "裕日車",
      "market": "TWSE",
      "foreign_daily": [
        -9,
        15,
        15,
        -2,
        3,
        -18
      ],
      "dealer_daily": [
        0,
        -1,
        0,
        0,
        1,
        1
      ]
    },
    {
      "code": "6957",
      "name": "裕慶-KY",
      "market": "TWSE",
      "foreign_daily": [
        -11,
        37,
        2,
        3,
        17,
        -44
      ],
      "dealer_daily": [
        0,
        2,
        0,
        1,
        1,
        1
      ]
    },
    {
      "code": "3266",
      "name": "昇陽",
      "market": "TWSE",
      "foreign_daily": [
        -21,
        8,
        13,
        7,
        8,
        -11
      ],
      "dealer_daily": [
        4,
        -4,
        5,
        0,
        -1,
        1
      ]
    },
    {
      "code": "3557",
      "name": "嘉威",
      "market": "TWSE",
      "foreign_daily": [
        -35,
        -2,
        15,
        13,
        3,
        10
      ],
      "dealer_daily": [
        15,
        -12,
        1,
        1,
        0,
        3
      ]
    },
    {
      "code": "2723",
      "name": "美食-KY",
      "market": "TWSE",
      "foreign_daily": [
        -57,
        -5,
        44,
        51,
        -5,
        -25
      ],
      "dealer_daily": [
        4,
        -2,
        2,
        3,
        -3,
        -2
      ]
    },
    {
      "code": "6666",
      "name": "羅麗芬-KY",
      "market": "TWSE",
      "foreign_daily": [
        1,
        6,
        -1,
        3,
        -2,
        -5
      ],
      "dealer_daily": [
        2,
        0,
        0,
        0,
        0,
        -1
      ]
    },
    {
      "code": "5450",
      "name": "南良",
      "market": "TPEX",
      "foreign_daily": [
        6,
        91,
        -69,
        -3,
        -6,
        -17
      ],
      "dealer_daily": [
        0,
        1,
        0,
        0,
        -1,
        5
      ]
    },
    {
      "code": "7642",
      "name": "昶瑞機電",
      "market": "TPEX",
      "foreign_daily": [
        0,
        4,
        -2,
        -2,
        2,
        0
      ],
      "dealer_daily": [
        0,
        0,
        0,
        0,
        1,
        0
      ]
    },
    {
      "code": "5310",
      "name": "天剛",
      "market": "TPEX",
      "foreign_daily": [
        0,
        0,
        0,
        1,
        1,
        0
      ],
      "dealer_daily": [
        0,
        0,
        0,
        1,
        0,
        0
      ]
    },
    {
      "code": "8940",
      "name": "新天地",
      "market": "TWSE",
      "foreign_daily": [
        19,
        -7,
        -14,
        7,
        -4,
        0
      ],
      "dealer_daily": [
        5,
        1,
        0,
        0,
        0,
        -3
      ]
    },
    {
      "code": "4972",
      "name": "湯石照明",
      "market": "TPEX",
      "foreign_daily": [
        -1,
        -3,
        -1,
        3,
        3,
        0
      ],
      "dealer_daily": [
        0,
        0,
        0,
        0,
        1,
        0
      ]
    },
    {
      "code": "8433",
      "name": "弘帆",
      "market": "TPEX",
      "foreign_daily": [
        1,
        9,
        -9,
        -2,
        0,
        2
      ],
      "dealer_daily": [
        0,
        0,
        0,
        0,
        0,
        2
      ]
    }
  ]
}